Classfile /C:/Silvere/Encours/Developpement/Episteme/episteme-native/target/classes/org/episteme/nativ/mathematics/linearalgebra/backends/NativeMPFRSparseLinearAlgebraBackend.class
  Last modified 16 mai 2026; size 26082 bytes
  SHA-256 checksum cda4cce934ae64a968a3c0f502259e69605e732b11912276527a8bdbe4125b25
  Compiled from "NativeMPFRSparseLinearAlgebraBackend.java"
public class org.episteme.nativ.mathematics.linearalgebra.backends.NativeMPFRSparseLinearAlgebraBackend<E extends java.lang.Object> extends java.lang.Object implements SparseLinearAlgebraProvider<E>, org.episteme.nativ.technical.backend.nativ.NativeBackend, CPUBackend
  minor version: 0
  major version: 69
  flags: (0x0021) ACC_PUBLIC, ACC_SUPER
  this_class: #1                          // org/episteme/nativ/mathematics/linearalgebra/backends/NativeMPFRSparseLinearAlgebraBackend
  super_class: #3                         // java/lang/Object
  interfaces: 1, fields: 4, methods: 98, attributes: 6
Constant pool:
    #1 = Class              #2            // org/episteme/nativ/mathematics/linearalgebra/backends/NativeMPFRSparseLinearAlgebraBackend
    #2 = Utf8               org/episteme/nativ/mathematics/linearalgebra/backends/NativeMPFRSparseLinearAlgebraBackend
    #3 = Class              #4            // java/lang/Object
    #4 = Utf8               java/lang/Object
    #5 = Class              #6            // org/episteme/nativ/technical/backend/nativ/NativeBackend
    #6 = Utf8               org/episteme/nativ/technical/backend/nativ/NativeBackend
    #7 = Utf8               logger
    #8 = Utf8               Lorg/slf4j/Logger;
    #9 = Utf8               MPFR_LAYOUT
   #10 = Utf8               Ljava/lang/foreign/MemoryLayout;
   #11 = Utf8               AVAILABLE
   #12 = Utf8               Z
   #13 = Utf8               closed
   #14 = Utf8               <init>
   #15 = Utf8               ()V
   #16 = Utf8               Code
   #17 = Class              #18           // java/lang/Error
   #18 = Utf8               java/lang/Error
   #19 = String             #20           // Unresolved compilation problems: \n\tThe import org.episteme.core cannot be resolved\n\tThe import org.episteme.core cannot be resolved\n\tThe import org.episteme.core cannot be resolved\n\tThe import org.episteme.core cannot be resolved\n\tThe import org.episteme.core cannot be resolved\n\tThe import org.episteme.core cannot be resolved\n\tThe import org.episteme.core cannot be resolved\n\tThe import org.episteme.core cannot be resolved\n\tThe import org.episteme.core cannot be resolved\n\tThe import org.episteme.core cannot be resolved\n\tThe import org.episteme.core cannot be resolved\n\torg.episteme.core cannot be resolved to a type\n\torg.episteme.core cannot be resolved to a type\n\tLinearAlgebraProvider cannot be resolved to a type\n\tSparseLinearAlgebraProvider cannot be resolved to a type\n\tCPUBackend cannot be resolved to a type\n\torg.episteme.core cannot be resolved to a type\n\tSparseLinearAlgebraProvider cannot be resolved to a type\n\tCPUBackend cannot be resolved to a type\n\tThe method isAvailable() of type NativeMPFRSparseLinearAlgebraBackend<E> must override or implement a supertype method\n\tThe method getId() of type NativeMPFRSparseLinearAlgebraBackend<E> must override or implement a supertype method\n\tThe method getName() of type NativeMPFRSparseLinearAlgebraBackend<E> must override or implement a supertype method\n\tThe method getDescription() of type NativeMPFRSparseLinearAlgebraBackend<E> must override or implement a supertype method\n\tThe method getType() of type NativeMPFRSparseLinearAlgebraBackend<E> must override or implement a supertype method\n\tThe method getPriority() of type NativeMPFRSparseLinearAlgebraBackend<E> must override or implement a supertype method\n\torg.episteme.core cannot be resolved to a type\n\tThe method createBackend() of type NativeMPFRSparseLinearAlgebraBackend<E> must override or implement a supertype method\n\torg.episteme.core cannot be resolved to a type\n\torg.episteme.core cannot be resolved to a type\n\tThe method close() of type new ExecutionContext(){} must override or implement a supertype method\n\tThe method isExplicitlyDisabled() of type NativeMPFRSparseLinearAlgebraBackend<E> must override or implement a supertype method\n\tThe method shutdown() of type NativeMPFRSparseLinearAlgebraBackend<E> must override or implement a supertype method\n\tThe method getMetadata() of type NativeMPFRSparseLinearAlgebraBackend<E> must override or implement a supertype method\n\torg.episteme.core cannot be resolved to a type\n\torg.episteme.core cannot be resolved to a type\n\torg.episteme.core.mathematics.context cannot be resolved\n\tMatrix cannot be resolved to a type\n\tMatrix cannot be resolved to a type\n\tReal cannot be resolved to a type\n\tThe method getRealPart(Object) from the type NativeMPFRSparseLinearAlgebraBackend<E> refers to the missing type Real\n\tMatrix cannot be resolved to a type\n\tRing cannot be resolved to a type\n\tRing cannot be resolved to a type\n\tRing cannot be resolved to a type\n\tReal cannot be resolved to a type\n\tReal cannot be resolved to a type\n\tMatrix cannot be resolved to a type\n\tReal cannot be resolved to a type\n\tReal cannot be resolved to a type\n\tMatrix cannot be resolved to a type\n\tComplex cannot be resolved to a type\n\tRing cannot be resolved to a type\n\tRing cannot be resolved to a type\n\tComplex cannot be resolved to a type\n\torg.episteme.core cannot be resolved to a type\n\torg.episteme.core cannot be resolved to a type\n\tMatrix cannot be resolved to a type\n\tVector cannot be resolved to a type\n\tMatrix cannot be resolved to a type\n\tVector cannot be resolved to a type\n\tVector cannot be resolved to a type\n\tMatrix cannot be resolved to a type\n\tMatrix cannot be resolved to a type\n\tComplex cannot be resolved to a type\n\tComplex cannot be resolved to a type\n\tComplex cannot be resolved to a type\n\tComplex cannot be resolved to a type\n\tComplex cannot be resolved\n\tThe method readMPFR(MemorySegment, Arena) from the type NativeMPFRSparseLinearAlgebraBackend<E> refers to the missing type Real\n\tThe method readMPFR(MemorySegment, Arena) from the type NativeMPFRSparseLinearAlgebraBackend<E> refers to the missing type Real\n\tReal cannot be resolved to a type\n\tReal cannot be resolved to a type\n\tReal cannot be resolved to a type\n\tReal cannot be resolved to a type\n\tThe method readMPFR(MemorySegment, Arena) from the type NativeMPFRSparseLinearAlgebraBackend<E> refers to the missing type Real\n\tVector cannot be resolved to a type\n\tVector cannot be resolved to a type\n\tMatrix cannot be resolved to a type\n\tMatrix cannot be resolved to a type\n\tMatrix cannot be resolved to a type\n\tMatrix cannot be resolved to a type\n\torg.episteme.core cannot be resolved to a type\n\tMatrix cannot be resolved to a type\n\tMatrix cannot be resolved to a type\n\tMatrix cannot be resolved to a type\n\tMatrix cannot be resolved to a type\n\tMatrix cannot be resolved to a type\n\tMatrix cannot be resolved to a type\n\tMatrix cannot be resolved to a type\n\tMatrix cannot be resolved to a type\n\tMatrix cannot be resolved to a type\n\tMatrix cannot be resolved to a type\n\tMatrix cannot be resolved to a type\n\tMatrix cannot be resolved to a type\n\tMatrix cannot be resolved to a type\n\tMatrix cannot be resolved to a type\n\tMatrix cannot be resolved to a type\n\tMatrix cannot be resolved to a type\n\tMatrix cannot be resolved to a type\n\tMatrix cannot be resolved to a type\n
   #20 = Utf8               Unresolved compilation problems: \n\tThe import org.episteme.core cannot be resolved\n\tThe import org.episteme.core cannot be resolved\n\tThe import org.episteme.core cannot be resolved\n\tThe import org.episteme.core cannot be resolved\n\tThe import org.episteme.core cannot be resolved\n\tThe import org.episteme.core cannot be resolved\n\tThe import org.episteme.core cannot be resolved\n\tThe import org.episteme.core cannot be resolved\n\tThe import org.episteme.core cannot be resolved\n\tThe import org.episteme.core cannot be resolved\n\tThe import org.episteme.core cannot be resolved\n\torg.episteme.core cannot be resolved to a type\n\torg.episteme.core cannot be resolved to a type\n\tLinearAlgebraProvider cannot be resolved to a type\n\tSparseLinearAlgebraProvider cannot be resolved to a type\n\tCPUBackend cannot be resolved to a type\n\torg.episteme.core cannot be resolved to a type\n\tSparseLinearAlgebraProvider cannot be resolved to a type\n\tCPUBackend cannot be resolved to a type\n\tThe method isAvailable() of type NativeMPFRSparseLinearAlgebraBackend<E> must override or implement a supertype method\n\tThe method getId() of type NativeMPFRSparseLinearAlgebraBackend<E> must override or implement a supertype method\n\tThe method getName() of type NativeMPFRSparseLinearAlgebraBackend<E> must override or implement a supertype method\n\tThe method getDescription() of type NativeMPFRSparseLinearAlgebraBackend<E> must override or implement a supertype method\n\tThe method getType() of type NativeMPFRSparseLinearAlgebraBackend<E> must override or implement a supertype method\n\tThe method getPriority() of type NativeMPFRSparseLinearAlgebraBackend<E> must override or implement a supertype method\n\torg.episteme.core cannot be resolved to a type\n\tThe method createBackend() of type NativeMPFRSparseLinearAlgebraBackend<E> must override or implement a supertype method\n\torg.episteme.core cannot be resolved to a type\n\torg.episteme.core cannot be resolved to a type\n\tThe method close() of type new ExecutionContext(){} must override or implement a supertype method\n\tThe method isExplicitlyDisabled() of type NativeMPFRSparseLinearAlgebraBackend<E> must override or implement a supertype method\n\tThe method shutdown() of type NativeMPFRSparseLinearAlgebraBackend<E> must override or implement a supertype method\n\tThe method getMetadata() of type NativeMPFRSparseLinearAlgebraBackend<E> must override or implement a supertype method\n\torg.episteme.core cannot be resolved to a type\n\torg.episteme.core cannot be resolved to a type\n\torg.episteme.core.mathematics.context cannot be resolved\n\tMatrix cannot be resolved to a type\n\tMatrix cannot be resolved to a type\n\tReal cannot be resolved to a type\n\tThe method getRealPart(Object) from the type NativeMPFRSparseLinearAlgebraBackend<E> refers to the missing type Real\n\tMatrix cannot be resolved to a type\n\tRing cannot be resolved to a type\n\tRing cannot be resolved to a type\n\tRing cannot be resolved to a type\n\tReal cannot be resolved to a type\n\tReal cannot be resolved to a type\n\tMatrix cannot be resolved to a type\n\tReal cannot be resolved to a type\n\tReal cannot be resolved to a type\n\tMatrix cannot be resolved to a type\n\tComplex cannot be resolved to a type\n\tRing cannot be resolved to a type\n\tRing cannot be resolved to a type\n\tComplex cannot be resolved to a type\n\torg.episteme.core cannot be resolved to a type\n\torg.episteme.core cannot be resolved to a type\n\tMatrix cannot be resolved to a type\n\tVector cannot be resolved to a type\n\tMatrix cannot be resolved to a type\n\tVector cannot be resolved to a type\n\tVector cannot be resolved to a type\n\tMatrix cannot be resolved to a type\n\tMatrix cannot be resolved to a type\n\tComplex cannot be resolved to a type\n\tComplex cannot be resolved to a type\n\tComplex cannot be resolved to a type\n\tComplex cannot be resolved to a type\n\tComplex cannot be resolved\n\tThe method readMPFR(MemorySegment, Arena) from the type NativeMPFRSparseLinearAlgebraBackend<E> refers to the missing type Real\n\tThe method readMPFR(MemorySegment, Arena) from the type NativeMPFRSparseLinearAlgebraBackend<E> refers to the missing type Real\n\tReal cannot be resolved to a type\n\tReal cannot be resolved to a type\n\tReal cannot be resolved to a type\n\tReal cannot be resolved to a type\n\tThe method readMPFR(MemorySegment, Arena) from the type NativeMPFRSparseLinearAlgebraBackend<E> refers to the missing type Real\n\tVector cannot be resolved to a type\n\tVector cannot be resolved to a type\n\tMatrix cannot be resolved to a type\n\tMatrix cannot be resolved to a type\n\tMatrix cannot be resolved to a type\n\tMatrix cannot be resolved to a type\n\torg.episteme.core cannot be resolved to a type\n\tMatrix cannot be resolved to a type\n\tMatrix cannot be resolved to a type\n\tMatrix cannot be resolved to a type\n\tMatrix cannot be resolved to a type\n\tMatrix cannot be resolved to a type\n\tMatrix cannot be resolved to a type\n\tMatrix cannot be resolved to a type\n\tMatrix cannot be resolved to a type\n\tMatrix cannot be resolved to a type\n\tMatrix cannot be resolved to a type\n\tMatrix cannot be resolved to a type\n\tMatrix cannot be resolved to a type\n\tMatrix cannot be resolved to a type\n\tMatrix cannot be resolved to a type\n\tMatrix cannot be resolved to a type\n\tMatrix cannot be resolved to a type\n\tMatrix cannot be resolved to a type\n\tMatrix cannot be resolved to a type\n
   #21 = Methodref          #17.#22       // java/lang/Error."<init>":(Ljava/lang/String;)V
   #22 = NameAndType        #14:#23       // "<init>":(Ljava/lang/String;)V
   #23 = Utf8               (Ljava/lang/String;)V
   #24 = Utf8               LineNumberTable
   #25 = Utf8               LocalVariableTable
   #26 = Utf8               this
   #27 = Utf8               Lorg/episteme/nativ/mathematics/linearalgebra/backends/NativeMPFRSparseLinearAlgebraBackend;
   #28 = Utf8               LocalVariableTypeTable
   #29 = Utf8               Lorg/episteme/nativ/mathematics/linearalgebra/backends/NativeMPFRSparseLinearAlgebraBackend<TE;>;
   #30 = Utf8               ensureInitialized
   #31 = String             #32           // Unresolved compilation problem: \n
   #32 = Utf8               Unresolved compilation problem: \n
   #33 = Utf8               ensureAlive
   #34 = Utf8               isAlive
   #35 = Utf8               ()Z
   #36 = Utf8               isAvailable
   #37 = String             #38           // Unresolved compilation problem: \n\tThe method isAvailable() of type NativeMPFRSparseLinearAlgebraBackend<E> must override or implement a supertype method\n
   #38 = Utf8               Unresolved compilation problem: \n\tThe method isAvailable() of type NativeMPFRSparseLinearAlgebraBackend<E> must override or implement a supertype method\n
   #39 = Utf8               getId
   #40 = Utf8               ()Ljava/lang/String;
   #41 = String             #42           // Unresolved compilation problem: \n\tThe method getId() of type NativeMPFRSparseLinearAlgebraBackend<E> must override or implement a supertype method\n
   #42 = Utf8               Unresolved compilation problem: \n\tThe method getId() of type NativeMPFRSparseLinearAlgebraBackend<E> must override or implement a supertype method\n
   #43 = Utf8               getName
   #44 = String             #45           // Unresolved compilation problem: \n\tThe method getName() of type NativeMPFRSparseLinearAlgebraBackend<E> must override or implement a supertype method\n
   #45 = Utf8               Unresolved compilation problem: \n\tThe method getName() of type NativeMPFRSparseLinearAlgebraBackend<E> must override or implement a supertype method\n
   #46 = Utf8               getDescription
   #47 = String             #48           // Unresolved compilation problem: \n\tThe method getDescription() of type NativeMPFRSparseLinearAlgebraBackend<E> must override or implement a supertype method\n
   #48 = Utf8               Unresolved compilation problem: \n\tThe method getDescription() of type NativeMPFRSparseLinearAlgebraBackend<E> must override or implement a supertype method\n
   #49 = Utf8               getType
   #50 = String             #51           // Unresolved compilation problem: \n\tThe method getType() of type NativeMPFRSparseLinearAlgebraBackend<E> must override or implement a supertype method\n
   #51 = Utf8               Unresolved compilation problem: \n\tThe method getType() of type NativeMPFRSparseLinearAlgebraBackend<E> must override or implement a supertype method\n
   #52 = Utf8               getPriority
   #53 = Utf8               ()I
   #54 = String             #55           // Unresolved compilation problem: \n\tThe method getPriority() of type NativeMPFRSparseLinearAlgebraBackend<E> must override or implement a supertype method\n
   #55 = Utf8               Unresolved compilation problem: \n\tThe method getPriority() of type NativeMPFRSparseLinearAlgebraBackend<E> must override or implement a supertype method\n
   #56 = Utf8               getAcceleratorType
   #57 = Utf8               ()Lorg/episteme/core/technical/backend/HardwareAccelerator;
   #58 = String             #59           // Unresolved compilation problem: \n\torg.episteme.core cannot be resolved to a type\n
   #59 = Utf8               Unresolved compilation problem: \n\torg.episteme.core cannot be resolved to a type\n
   #60 = Utf8               isLoaded
   #61 = Utf8               getNativeLibraryName
   #62 = Utf8               createBackend
   #63 = Utf8               ()Ljava/lang/Object;
   #64 = String             #65           // Unresolved compilation problem: \n\tThe method createBackend() of type NativeMPFRSparseLinearAlgebraBackend<E> must override or implement a supertype method\n
   #65 = Utf8               Unresolved compilation problem: \n\tThe method createBackend() of type NativeMPFRSparseLinearAlgebraBackend<E> must override or implement a supertype method\n
   #66 = Utf8               createContext
   #67 = Utf8               ()Lorg/episteme/core/technical/backend/ExecutionContext;
   #68 = String             #69           // Unresolved compilation problems: \n\torg.episteme.core cannot be resolved to a type\n\torg.episteme.core cannot be resolved to a type\n\tThe method close() of type new ExecutionContext(){} must override or implement a supertype method\n
   #69 = Utf8               Unresolved compilation problems: \n\torg.episteme.core cannot be resolved to a type\n\torg.episteme.core cannot be resolved to a type\n\tThe method close() of type new ExecutionContext(){} must override or implement a supertype method\n
   #70 = Utf8               isExplicitlyDisabled
   #71 = String             #72           // Unresolved compilation problem: \n\tThe method isExplicitlyDisabled() of type NativeMPFRSparseLinearAlgebraBackend<E> must override or implement a supertype method\n
   #72 = Utf8               Unresolved compilation problem: \n\tThe method isExplicitlyDisabled() of type NativeMPFRSparseLinearAlgebraBackend<E> must override or implement a supertype method\n
   #73 = Utf8               shutdown
   #74 = String             #75           // Unresolved compilation problem: \n\tThe method shutdown() of type NativeMPFRSparseLinearAlgebraBackend<E> must override or implement a supertype method\n
   #75 = Utf8               Unresolved compilation problem: \n\tThe method shutdown() of type NativeMPFRSparseLinearAlgebraBackend<E> must override or implement a supertype method\n
   #76 = Utf8               getMetadata
   #77 = Utf8               ()Ljava/util/Map;
   #78 = Utf8               Signature
   #79 = Utf8               ()Ljava/util/Map<Ljava/lang/String;Ljava/lang/String;>;
   #80 = String             #81           // Unresolved compilation problem: \n\tThe method getMetadata() of type NativeMPFRSparseLinearAlgebraBackend<E> must override or implement a supertype method\n
   #81 = Utf8               Unresolved compilation problem: \n\tThe method getMetadata() of type NativeMPFRSparseLinearAlgebraBackend<E> must override or implement a supertype method\n
   #82 = Utf8               score
   #83 = Utf8               (Lorg/episteme/core/technical/algorithm/OperationContext;)D
   #84 = Utf8               getPrecision
   #85 = Utf8               ()J
   #86 = String             #87           // Unresolved compilation problem: \n\torg.episteme.core.mathematics.context cannot be resolved\n
   #87 = Utf8               Unresolved compilation problem: \n\torg.episteme.core.mathematics.context cannot be resolved\n
   #88 = Utf8               trace
   #89 = Utf8               (LMatrix;)Ljava/lang/Object;
   #90 = Utf8               (LMatrix<TE;>;)TE;
   #91 = String             #92           // Unresolved compilation problem: \n\tMatrix cannot be resolved to a type\n
   #92 = Utf8               Unresolved compilation problem: \n\tMatrix cannot be resolved to a type\n
   #93 = Utf8               track
   #94 = Utf8               (Lorg/episteme/nativ/technical/backend/nativ/ResourceTracker;Ljava/lang/foreign/MemorySegment;)V
   #95 = Utf8               trackArray
   #96 = Utf8               (Lorg/episteme/nativ/technical/backend/nativ/ResourceTracker;Ljava/lang/foreign/MemorySegment;I)V
   #97 = Utf8               readMPFR
   #98 = Utf8               (Ljava/lang/foreign/MemorySegment;Ljava/lang/foreign/Arena;)LReal;
   #99 = String             #100          // Unresolved compilation problem: \n\tReal cannot be resolved to a type\n
  #100 = Utf8               Unresolved compilation problem: \n\tReal cannot be resolved to a type\n
  #101 = Utf8               setMPFR_internal
  #102 = Utf8               (Ljava/lang/foreign/MemorySegment;Ljava/lang/foreign/MemorySegment;Ljava/lang/Object;Ljava/lang/foreign/Arena;)V
  #103 = Utf8               Exceptions
  #104 = Class              #105          // java/lang/Throwable
  #105 = Utf8               java/lang/Throwable
  #106 = String             #107          // Unresolved compilation problem: \n\tThe method getRealPart(Object) from the type NativeMPFRSparseLinearAlgebraBackend<E> refers to the missing type Real\n
  #107 = Utf8               Unresolved compilation problem: \n\tThe method getRealPart(Object) from the type NativeMPFRSparseLinearAlgebraBackend<E> refers to the missing type Real\n
  #108 = Utf8               isComplex
  #109 = Utf8               (Ljava/lang/Object;)Z
  #110 = Utf8               isComplexRing
  #111 = Utf8               (LRing;)Z
  #112 = Utf8               (LRing<*>;)Z
  #113 = String             #114          // Unresolved compilation problem: \n\tRing cannot be resolved to a type\n
  #114 = Utf8               Unresolved compilation problem: \n\tRing cannot be resolved to a type\n
  #115 = Utf8               castScalar
  #116 = Utf8               (Ljava/lang/Object;LRing;)Ljava/lang/Object;
  #117 = Utf8               (Ljava/lang/Object;LRing<TE;>;)TE;
  #118 = Utf8               isZero
  #119 = Utf8               (Ljava/lang/Object;LRing;)Z
  #120 = Utf8               (Ljava/lang/Object;LRing<*>;)Z
  #121 = Utf8               getRealValue
  #122 = Utf8               (Ljava/lang/Object;)D
  #123 = Utf8               getReal
  #124 = Utf8               (Ljava/lang/Object;)LReal;
  #125 = Utf8               setMPFR
  #126 = Utf8               (Ljava/lang/foreign/MemorySegment;Ljava/lang/Object;Ljava/lang/foreign/Arena;)V
  #127 = Utf8               (Ljava/lang/foreign/MemorySegment;TE;Ljava/lang/foreign/Arena;)V
  #128 = Utf8               initVector
  #129 = Utf8               (LMatrix;Ljava/lang/foreign/Arena;Lorg/episteme/nativ/technical/backend/nativ/ResourceTracker;JZ)Ljava/lang/foreign/MemorySegment;
  #130 = Utf8               (LMatrix<TE;>;Ljava/lang/foreign/Arena;Lorg/episteme/nativ/technical/backend/nativ/ResourceTracker;JZ)Ljava/lang/foreign/MemorySegment;
  #131 = Utf8               getRealPart
  #132 = Utf8               getImagPart
  #133 = Utf8               dotProduct
  #134 = Utf8               (Ljava/lang/foreign/MemorySegment;Ljava/lang/foreign/MemorySegment;ILjava/lang/foreign/MemorySegment;JLjava/lang/foreign/Arena;Z)V
  #135 = Utf8               multiply
  #136 = Utf8               (LMatrix;LVector;)LVector;
  #137 = Utf8               (LMatrix<TE;>;LVector<TE;>;)LVector<TE;>;
  #138 = Utf8               axpy_internal
  #139 = Utf8               (Ljava/lang/foreign/MemorySegment;Ljava/lang/Object;Ljava/lang/foreign/MemorySegment;IJLjava/lang/foreign/Arena;Lorg/episteme/nativ/technical/backend/nativ/ResourceTracker;Z)V
  #140 = Utf8               (Ljava/lang/foreign/MemorySegment;TE;Ljava/lang/foreign/MemorySegment;IJLjava/lang/foreign/Arena;Lorg/episteme/nativ/technical/backend/nativ/ResourceTracker;Z)V
  #141 = String             #142          // Unresolved compilation problem: \n\tComplex cannot be resolved to a type\n
  #142 = Utf8               Unresolved compilation problem: \n\tComplex cannot be resolved to a type\n
  #143 = Utf8               dot_internal
  #144 = Utf8               (Ljava/lang/foreign/MemorySegment;Ljava/lang/foreign/MemorySegment;IJLjava/lang/foreign/Arena;Lorg/episteme/nativ/technical/backend/nativ/ResourceTracker;ZLRing;)Ljava/lang/Object;
  #145 = Utf8               (Ljava/lang/foreign/MemorySegment;Ljava/lang/foreign/MemorySegment;IJLjava/lang/foreign/Arena;Lorg/episteme/nativ/technical/backend/nativ/ResourceTracker;ZLRing<TE;>;)TE;
  #146 = Utf8               norm_internal
  #147 = Utf8               (Ljava/lang/foreign/MemorySegment;IJLjava/lang/foreign/Arena;Lorg/episteme/nativ/technical/backend/nativ/ResourceTracker;ZLRing;)Ljava/lang/Object;
  #148 = Utf8               (Ljava/lang/foreign/MemorySegment;IJLjava/lang/foreign/Arena;Lorg/episteme/nativ/technical/backend/nativ/ResourceTracker;ZLRing<TE;>;)TE;
  #149 = Utf8               copy_internal
  #150 = Utf8               (Ljava/lang/foreign/MemorySegment;Ljava/lang/foreign/MemorySegment;IZ)V
  #151 = Utf8               scale_internal
  #152 = Utf8               (Ljava/lang/foreign/MemorySegment;Ljava/lang/Object;IJLjava/lang/foreign/Arena;Lorg/episteme/nativ/technical/backend/nativ/ResourceTracker;Z)V
  #153 = Utf8               (Ljava/lang/foreign/MemorySegment;TE;IJLjava/lang/foreign/Arena;Lorg/episteme/nativ/technical/backend/nativ/ResourceTracker;Z)V
  #154 = Utf8               initNativeValues
  #155 = Utf8               ([Ljava/lang/Object;JLjava/lang/foreign/Arena;Lorg/episteme/nativ/technical/backend/nativ/ResourceTracker;Z)Ljava/lang/foreign/MemorySegment;
  #156 = Utf8               scale
  #157 = Utf8               (Ljava/lang/Object;LMatrix;)LMatrix;
  #158 = Utf8               (TE;LMatrix<TE;>;)LMatrix<TE;>;
  #159 = Utf8               (LVector;Ljava/lang/Object;)LVector;
  #160 = Utf8               (LVector<TE;>;TE;)LVector<TE;>;
  #161 = String             #162          // Unresolved compilation problem: \n\tVector cannot be resolved to a type\n
  #162 = Utf8               Unresolved compilation problem: \n\tVector cannot be resolved to a type\n
  #163 = Utf8               add
  #164 = Utf8               (LMatrix;LMatrix;)LMatrix;
  #165 = Utf8               (LMatrix<TE;>;LMatrix<TE;>;)LMatrix<TE;>;
  #166 = Utf8               (LVector;LVector;)LVector;
  #167 = Utf8               (LVector<TE;>;LVector<TE;>;)LVector<TE;>;
  #168 = Utf8               subtract
  #169 = String             #170          // Unresolved compilation problems: \n\tMatrix cannot be resolved to a type\n\tComplex cannot be resolved to a type\n\tComplex cannot be resolved to a type\n\tComplex cannot be resolved to a type\n\tComplex cannot be resolved to a type\n\tComplex cannot be resolved\n\tThe method readMPFR(MemorySegment, Arena) from the type NativeMPFRSparseLinearAlgebraBackend<E> refers to the missing type Real\n\tThe method readMPFR(MemorySegment, Arena) from the type NativeMPFRSparseLinearAlgebraBackend<E> refers to the missing type Real\n\tReal cannot be resolved to a type\n\tReal cannot be resolved to a type\n\tReal cannot be resolved to a type\n\tReal cannot be resolved to a type\n\tThe method readMPFR(MemorySegment, Arena) from the type NativeMPFRSparseLinearAlgebraBackend<E> refers to the missing type Real\n
  #170 = Utf8               Unresolved compilation problems: \n\tMatrix cannot be resolved to a type\n\tComplex cannot be resolved to a type\n\tComplex cannot be resolved to a type\n\tComplex cannot be resolved to a type\n\tComplex cannot be resolved to a type\n\tComplex cannot be resolved\n\tThe method readMPFR(MemorySegment, Arena) from the type NativeMPFRSparseLinearAlgebraBackend<E> refers to the missing type Real\n\tThe method readMPFR(MemorySegment, Arena) from the type NativeMPFRSparseLinearAlgebraBackend<E> refers to the missing type Real\n\tReal cannot be resolved to a type\n\tReal cannot be resolved to a type\n\tReal cannot be resolved to a type\n\tReal cannot be resolved to a type\n\tThe method readMPFR(MemorySegment, Arena) from the type NativeMPFRSparseLinearAlgebraBackend<E> refers to the missing type Real\n
  #171 = Utf8               dot
  #172 = Utf8               (LVector;LVector;)Ljava/lang/Object;
  #173 = Utf8               (LVector<TE;>;LVector<TE;>;)TE;
  #174 = Utf8               norm
  #175 = Utf8               (LVector;)Ljava/lang/Object;
  #176 = Utf8               (LVector<TE;>;)TE;
  #177 = Utf8               solve
  #178 = Utf8               isLowerTriangular
  #179 = Utf8               (LMatrix;)Z
  #180 = Utf8               (LMatrix<TE;>;)Z
  #181 = Utf8               isUpperTriangular
  #182 = Utf8               solveTriangular
  #183 = Utf8               (LMatrix;LVector;ZZZZ)LVector;
  #184 = Utf8               (LMatrix<TE;>;LVector<TE;>;ZZZZ)LVector<TE;>;
  #185 = Utf8               complexDiv
  #186 = Utf8               (Ljava/lang/foreign/MemorySegment;Ljava/lang/foreign/MemorySegment;Ljava/lang/foreign/MemorySegment;Ljava/lang/foreign/MemorySegment;Ljava/lang/foreign/MemorySegment;Ljava/lang/foreign/MemorySegment;JLjava/lang/foreign/Arena;)V
  #187 = Utf8               transpose
  #188 = Utf8               (LMatrix;)LMatrix;
  #189 = Utf8               (LMatrix<TE;>;)LMatrix<TE;>;
  #190 = Utf8               exp
  #191 = Utf8               log
  #192 = Utf8               log10
  #193 = Utf8               sin
  #194 = Utf8               cos
  #195 = Utf8               tan
  #196 = Utf8               asin
  #197 = Utf8               acos
  #198 = Utf8               atan
  #199 = Utf8               sinh
  #200 = Utf8               cosh
  #201 = Utf8               tanh
  #202 = Utf8               asinh
  #203 = Utf8               acosh
  #204 = Utf8               atanh
  #205 = Utf8               sqrt
  #206 = Utf8               cbrt
  #207 = Utf8               applyTranscendental
  #208 = Utf8               (LMatrix;Ljava/lang/String;[Ljava/lang/Object;)LMatrix;
  #209 = Utf8               (LMatrix<TE;>;Ljava/lang/String;[Ljava/lang/Object;)LMatrix<TE;>;
  #210 = Utf8               conjugateGradient
  #211 = Utf8               (LMatrix;LVector;LVector;Ljava/lang/Object;I)LVector;
  #212 = Utf8               (LMatrix<TE;>;LVector<TE;>;LVector<TE;>;TE;I)LVector<TE;>;
  #213 = Utf8               bicgstab
  #214 = Utf8               gmres
  #215 = Utf8               (LMatrix;LVector;LVector;Ljava/lang/Object;II)LVector;
  #216 = Utf8               (LMatrix<TE;>;LVector<TE;>;LVector<TE;>;TE;II)LVector<TE;>;
  #217 = Utf8               solveSmallAndCheck
  #218 = Utf8               ([[Ljava/lang/Object;Ljava/lang/Object;Ljava/lang/foreign/MemorySegment;Ljava/lang/foreign/MemorySegment;IIZLRing;JLjava/lang/foreign/Arena;Lorg/episteme/nativ/technical/backend/nativ/ResourceTracker;)V
  #219 = Utf8               ([[Ljava/lang/Object;TE;Ljava/lang/foreign/MemorySegment;Ljava/lang/foreign/MemorySegment;IIZLRing<TE;>;JLjava/lang/foreign/Arena;Lorg/episteme/nativ/technical/backend/nativ/ResourceTracker;)V
  #220 = Utf8               compare
  #221 = Utf8               (Ljava/lang/Object;Ljava/lang/Object;)I
  #222 = Utf8               (TE;TE;)I
  #223 = Utf8               negate
  #224 = Utf8               (ZLjava/lang/Object;)Ljava/lang/Object;
  #225 = Utf8               (ZTE;)TE;
  #226 = Utf8               divide
  #227 = Utf8               (ZLjava/lang/Object;Ljava/lang/Object;)Ljava/lang/Object;
  #228 = Utf8               (ZTE;TE;)TE;
  #229 = Utf8               backToVector
  #230 = Utf8               (Ljava/lang/foreign/MemorySegment;IZLRing;Ljava/lang/foreign/Arena;)LVector;
  #231 = Utf8               (Ljava/lang/foreign/MemorySegment;IZLRing<TE;>;Ljava/lang/foreign/Arena;)LVector<TE;>;
  #232 = Utf8               complexTranscendental
  #233 = Utf8               (Lorg/episteme/core/mathematics/numbers/complex/Complex;Ljava/lang/String;JLjava/lang/foreign/Arena;[Ljava/lang/Object;)Lorg/episteme/core/mathematics/numbers/complex/Complex;
  #234 = Utf8               realTranscendental
  #235 = Utf8               (LReal;Ljava/lang/String;JLjava/lang/foreign/Arena;[Ljava/lang/Object;)LReal;
  #236 = Utf8               determinant
  #237 = Utf8               inverse
  #238 = Utf8               clearMPFRArray
  #239 = Utf8               (Ljava/lang/foreign/MemorySegment;I)V
  #240 = Utf8               normalize
  #241 = Utf8               (LVector;)LVector;
  #242 = Utf8               (LVector<TE;>;)LVector<TE;>;
  #243 = Utf8               cross
  #244 = Utf8               angle
  #245 = Utf8               projection
  #246 = Utf8               createScalar
  #247 = Utf8               (DLVector;)Ljava/lang/Object;
  #248 = Utf8               (DLVector<TE;>;)TE;
  #249 = Utf8               (Lorg/episteme/core/mathematics/numbers/real/Real;LVector;)Ljava/lang/Object;
  #250 = Utf8               (Lorg/episteme/core/mathematics/numbers/real/Real;LVector<TE;>;)TE;
  #251 = Utf8               SourceFile
  #252 = Utf8               NativeMPFRSparseLinearAlgebraBackend.java
  #253 = Utf8               <E:Ljava/lang/Object;>Ljava/lang/Object;LSparseLinearAlgebraProvider<TE;>;Lorg/episteme/nativ/technical/backend/nativ/NativeBackend;LCPUBackend;
  #254 = Utf8               RuntimeInvisibleAnnotations
  #255 = Utf8               Lcom/google/auto/service/AutoService;
  #256 = Utf8               value
  #257 = Utf8               Lorg/episteme/core/technical/backend/Backend;
  #258 = Utf8               Lorg/episteme/core/technical/backend/ComputeBackend;
  #259 = Utf8               Lorg/episteme/nativ/technical/backend/nativ/NativeBackend;
  #260 = Utf8               LLinearAlgebraProvider;
  #261 = Utf8               LSparseLinearAlgebraProvider;
  #262 = Utf8               LCPUBackend;
  #263 = Utf8               Lorg/episteme/core/technical/algorithm/AlgorithmProvider;
  #264 = Utf8               InconsistentHierarchy
  #265 = Class              #266          // CPUBackend
  #266 = Utf8               CPUBackend
  #267 = Class              #268          // Matrix
  #268 = Utf8               Matrix
  #269 = Class              #270          // Real
  #270 = Utf8               Real
  #271 = Class              #272          // Ring
  #272 = Utf8               Ring
  #273 = Class              #274          // SparseLinearAlgebraProvider
  #274 = Utf8               SparseLinearAlgebraProvider
  #275 = Class              #276          // Vector
  #276 = Utf8               Vector
  #277 = Class              #278          // org/episteme/core/mathematics/numbers/complex/Complex
  #278 = Utf8               org/episteme/core/mathematics/numbers/complex/Complex
  #279 = Class              #280          // org/episteme/core/mathematics/numbers/real/Real
  #280 = Utf8               org/episteme/core/mathematics/numbers/real/Real
  #281 = Class              #282          // org/episteme/core/technical/algorithm/OperationContext
  #282 = Utf8               org/episteme/core/technical/algorithm/OperationContext
  #283 = Class              #284          // org/episteme/core/technical/backend/ExecutionContext
  #284 = Utf8               org/episteme/core/technical/backend/ExecutionContext
  #285 = Class              #286          // org/episteme/core/technical/backend/HardwareAccelerator
  #286 = Utf8               org/episteme/core/technical/backend/HardwareAccelerator
  #287 = Utf8               MissingTypes
  #288 = Utf8               NestMembers
  #289 = Class              #290          // org/episteme/nativ/mathematics/linearalgebra/backends/NativeMPFRSparseLinearAlgebraBackend$1
  #290 = Utf8               org/episteme/nativ/mathematics/linearalgebra/backends/NativeMPFRSparseLinearAlgebraBackend$1
{
  private static final org.slf4j.Logger logger;
    descriptor: Lorg/slf4j/Logger;
    flags: (0x001a) ACC_PRIVATE, ACC_STATIC, ACC_FINAL

  private static final java.lang.foreign.MemoryLayout MPFR_LAYOUT;
    descriptor: Ljava/lang/foreign/MemoryLayout;
    flags: (0x001a) ACC_PRIVATE, ACC_STATIC, ACC_FINAL

  private static final boolean AVAILABLE;
    descriptor: Z
    flags: (0x001a) ACC_PRIVATE, ACC_STATIC, ACC_FINAL

  private volatile boolean closed;
    descriptor: Z
    flags: (0x0042) ACC_PRIVATE, ACC_VOLATILE

  public org.episteme.nativ.mathematics.linearalgebra.backends.NativeMPFRSparseLinearAlgebraBackend();
    descriptor: ()V
    flags: (0x0001) ACC_PUBLIC
    Code:
      stack=3, locals=1, args_size=1
         0: new           #17                 // class java/lang/Error
         3: dup
         4: ldc           #19                 // String Unresolved compilation problems: \n\tThe import org.episteme.core cannot be resolved\n\tThe import org.episteme.core cannot be resolved\n\tThe import org.episteme.core cannot be resolved\n\tThe import org.episteme.core cannot be resolved\n\tThe import org.episteme.core cannot be resolved\n\tThe import org.episteme.core cannot be resolved\n\tThe import org.episteme.core cannot be resolved\n\tThe import org.episteme.core cannot be resolved\n\tThe import org.episteme.core cannot be resolved\n\tThe import org.episteme.core cannot be resolved\n\tThe import org.episteme.core cannot be resolved\n\torg.episteme.core cannot be resolved to a type\n\torg.episteme.core cannot be resolved to a type\n\tLinearAlgebraProvider cannot be resolved to a type\n\tSparseLinearAlgebraProvider cannot be resolved to a type\n\tCPUBackend cannot be resolved to a type\n\torg.episteme.core cannot be resolved to a type\n\tSparseLinearAlgebraProvider cannot be resolved to a type\n\tCPUBackend cannot be resolved to a type\n\tThe method isAvailable() of type NativeMPFRSparseLinearAlgebraBackend<E> must override or implement a supertype method\n\tThe method getId() of type NativeMPFRSparseLinearAlgebraBackend<E> must override or implement a supertype method\n\tThe method getName() of type NativeMPFRSparseLinearAlgebraBackend<E> must override or implement a supertype method\n\tThe method getDescription() of type NativeMPFRSparseLinearAlgebraBackend<E> must override or implement a supertype method\n\tThe method getType() of type NativeMPFRSparseLinearAlgebraBackend<E> must override or implement a supertype method\n\tThe method getPriority() of type NativeMPFRSparseLinearAlgebraBackend<E> must override or implement a supertype method\n\torg.episteme.core cannot be resolved to a type\n\tThe method createBackend() of type NativeMPFRSparseLinearAlgebraBackend<E> must override or implement a supertype method\n\torg.episteme.core cannot be resolved to a type\n\torg.episteme.core cannot be resolved to a type\n\tThe method close() of type new ExecutionContext(){} must override or implement a supertype method\n\tThe method isExplicitlyDisabled() of type NativeMPFRSparseLinearAlgebraBackend<E> must override or implement a supertype method\n\tThe method shutdown() of type NativeMPFRSparseLinearAlgebraBackend<E> must override or implement a supertype method\n\tThe method getMetadata() of type NativeMPFRSparseLinearAlgebraBackend<E> must override or implement a supertype method\n\torg.episteme.core cannot be resolved to a type\n\torg.episteme.core cannot be resolved to a type\n\torg.episteme.core.mathematics.context cannot be resolved\n\tMatrix cannot be resolved to a type\n\tMatrix cannot be resolved to a type\n\tReal cannot be resolved to a type\n\tThe method getRealPart(Object) from the type NativeMPFRSparseLinearAlgebraBackend<E> refers to the missing type Real\n\tMatrix cannot be resolved to a type\n\tRing cannot be resolved to a type\n\tRing cannot be resolved to a type\n\tRing cannot be resolved to a type\n\tReal cannot be resolved to a type\n\tReal cannot be resolved to a type\n\tMatrix cannot be resolved to a type\n\tReal cannot be resolved to a type\n\tReal cannot be resolved to a type\n\tMatrix cannot be resolved to a type\n\tComplex cannot be resolved to a type\n\tRing cannot be resolved to a type\n\tRing cannot be resolved to a type\n\tComplex cannot be resolved to a type\n\torg.episteme.core cannot be resolved to a type\n\torg.episteme.core cannot be resolved to a type\n\tMatrix cannot be resolved to a type\n\tVector cannot be resolved to a type\n\tMatrix cannot be resolved to a type\n\tVector cannot be resolved to a type\n\tVector cannot be resolved to a type\n\tMatrix cannot be resolved to a type\n\tMatrix cannot be resolved to a type\n\tComplex cannot be resolved to a type\n\tComplex cannot be resolved to a type\n\tComplex cannot be resolved to a type\n\tComplex cannot be resolved to a type\n\tComplex cannot be resolved\n\tThe method readMPFR(MemorySegment, Arena) from the type NativeMPFRSparseLinearAlgebraBackend<E> refers to the missing type Real\n\tThe method readMPFR(MemorySegment, Arena) from the type NativeMPFRSparseLinearAlgebraBackend<E> refers to the missing type Real\n\tReal cannot be resolved to a type\n\tReal cannot be resolved to a type\n\tReal cannot be resolved to a type\n\tReal cannot be resolved to a type\n\tThe method readMPFR(MemorySegment, Arena) from the type NativeMPFRSparseLinearAlgebraBackend<E> refers to the missing type Real\n\tVector cannot be resolved to a type\n\tVector cannot be resolved to a type\n\tMatrix cannot be resolved to a type\n\tMatrix cannot be resolved to a type\n\tMatrix cannot be resolved to a type\n\tMatrix cannot be resolved to a type\n\torg.episteme.core cannot be resolved to a type\n\tMatrix cannot be resolved to a type\n\tMatrix cannot be resolved to a type\n\tMatrix cannot be resolved to a type\n\tMatrix cannot be resolved to a type\n\tMatrix cannot be resolved to a type\n\tMatrix cannot be resolved to a type\n\tMatrix cannot be resolved to a type\n\tMatrix cannot be resolved to a type\n\tMatrix cannot be resolved to a type\n\tMatrix cannot be resolved to a type\n\tMatrix cannot be resolved to a type\n\tMatrix cannot be resolved to a type\n\tMatrix cannot be resolved to a type\n\tMatrix cannot be resolved to a type\n\tMatrix cannot be resolved to a type\n\tMatrix cannot be resolved to a type\n\tMatrix cannot be resolved to a type\n\tMatrix cannot be resolved to a type\n
         6: invokespecial #21                 // Method java/lang/Error."<init>":(Ljava/lang/String;)V
         9: athrow
      LineNumberTable:
        line 11: 0
      LocalVariableTable:
        Start  Length  Slot  Name   Signature
            0      10     0  this   Lorg/episteme/nativ/mathematics/linearalgebra/backends/NativeMPFRSparseLinearAlgebraBackend;
      LocalVariableTypeTable:
        Start  Length  Slot  Name   Signature
            0      10     0  this   Lorg/episteme/nativ/mathematics/linearalgebra/backends/NativeMPFRSparseLinearAlgebraBackend<TE;>;

  private void ensureInitialized();
    descriptor: ()V
    flags: (0x0002) ACC_PRIVATE
    Code:
      stack=3, locals=1, args_size=1
         0: new           #17                 // class java/lang/Error
         3: dup
         4: ldc           #31                 // String Unresolved compilation problem: \n
         6: invokespecial #21                 // Method java/lang/Error."<init>":(Ljava/lang/String;)V
         9: athrow
      LineNumberTable:
        line 46: 0
      LocalVariableTable:
        Start  Length  Slot  Name   Signature
            0      10     0  this   Lorg/episteme/nativ/mathematics/linearalgebra/backends/NativeMPFRSparseLinearAlgebraBackend;
      LocalVariableTypeTable:
        Start  Length  Slot  Name   Signature
            0      10     0  this   Lorg/episteme/nativ/mathematics/linearalgebra/backends/NativeMPFRSparseLinearAlgebraBackend<TE;>;

  private void ensureAlive();
    descriptor: ()V
    flags: (0x0002) ACC_PRIVATE
    Code:
      stack=3, locals=1, args_size=1
         0: new           #17                 // class java/lang/Error
         3: dup
         4: ldc           #31                 // String Unresolved compilation problem: \n
         6: invokespecial #21                 // Method java/lang/Error."<init>":(Ljava/lang/String;)V
         9: athrow
      LineNumberTable:
        line 51: 0
      LocalVariableTable:
        Start  Length  Slot  Name   Signature
            0      10     0  this   Lorg/episteme/nativ/mathematics/linearalgebra/backends/NativeMPFRSparseLinearAlgebraBackend;
      LocalVariableTypeTable:
        Start  Length  Slot  Name   Signature
            0      10     0  this   Lorg/episteme/nativ/mathematics/linearalgebra/backends/NativeMPFRSparseLinearAlgebraBackend<TE;>;

  public boolean isAlive();
    descriptor: ()Z
    flags: (0x0001) ACC_PUBLIC
    Code:
      stack=3, locals=1, args_size=1
         0: new           #17                 // class java/lang/Error
         3: dup
         4: ldc           #31                 // String Unresolved compilation problem: \n
         6: invokespecial #21                 // Method java/lang/Error."<init>":(Ljava/lang/String;)V
         9: athrow
      LineNumberTable:
        line 55: 0
      LocalVariableTable:
        Start  Length  Slot  Name   Signature
            0      10     0  this   Lorg/episteme/nativ/mathematics/linearalgebra/backends/NativeMPFRSparseLinearAlgebraBackend;
      LocalVariableTypeTable:
        Start  Length  Slot  Name   Signature
            0      10     0  this   Lorg/episteme/nativ/mathematics/linearalgebra/backends/NativeMPFRSparseLinearAlgebraBackend<TE;>;

  public boolean isAvailable();
    descriptor: ()Z
    flags: (0x0001) ACC_PUBLIC
    Code:
      stack=3, locals=1, args_size=1
         0: new           #17                 // class java/lang/Error
         3: dup
         4: ldc           #37                 // String Unresolved compilation problem: \n\tThe method isAvailable() of type NativeMPFRSparseLinearAlgebraBackend<E> must override or implement a supertype method\n
         6: invokespecial #21                 // Method java/lang/Error."<init>":(Ljava/lang/String;)V
         9: athrow
      LineNumberTable:
        line 57: 0
      LocalVariableTable:
        Start  Length  Slot  Name   Signature
            0      10     0  this   Lorg/episteme/nativ/mathematics/linearalgebra/backends/NativeMPFRSparseLinearAlgebraBackend;
      LocalVariableTypeTable:
        Start  Length  Slot  Name   Signature
            0      10     0  this   Lorg/episteme/nativ/mathematics/linearalgebra/backends/NativeMPFRSparseLinearAlgebraBackend<TE;>;

  public java.lang.String getId();
    descriptor: ()Ljava/lang/String;
    flags: (0x0001) ACC_PUBLIC
    Code:
      stack=3, locals=1, args_size=1
         0: new           #17                 // class java/lang/Error
         3: dup
         4: ldc           #41                 // String Unresolved compilation problem: \n\tThe method getId() of type NativeMPFRSparseLinearAlgebraBackend<E> must override or implement a supertype method\n
         6: invokespecial #21                 // Method java/lang/Error."<init>":(Ljava/lang/String;)V
         9: athrow
      LineNumberTable:
        line 58: 0
      LocalVariableTable:
        Start  Length  Slot  Name   Signature
            0      10     0  this   Lorg/episteme/nativ/mathematics/linearalgebra/backends/NativeMPFRSparseLinearAlgebraBackend;
      LocalVariableTypeTable:
        Start  Length  Slot  Name   Signature
            0      10     0  this   Lorg/episteme/nativ/mathematics/linearalgebra/backends/NativeMPFRSparseLinearAlgebraBackend<TE;>;

  public java.lang.String getName();
    descriptor: ()Ljava/lang/String;
    flags: (0x0001) ACC_PUBLIC
    Code:
      stack=3, locals=1, args_size=1
         0: new           #17                 // class java/lang/Error
         3: dup
         4: ldc           #44                 // String Unresolved compilation problem: \n\tThe method getName() of type NativeMPFRSparseLinearAlgebraBackend<E> must override or implement a supertype method\n
         6: invokespecial #21                 // Method java/lang/Error."<init>":(Ljava/lang/String;)V
         9: athrow
      LineNumberTable:
        line 59: 0
      LocalVariableTable:
        Start  Length  Slot  Name   Signature
            0      10     0  this   Lorg/episteme/nativ/mathematics/linearalgebra/backends/NativeMPFRSparseLinearAlgebraBackend;
      LocalVariableTypeTable:
        Start  Length  Slot  Name   Signature
            0      10     0  this   Lorg/episteme/nativ/mathematics/linearalgebra/backends/NativeMPFRSparseLinearAlgebraBackend<TE;>;

  public java.lang.String getDescription();
    descriptor: ()Ljava/lang/String;
    flags: (0x0001) ACC_PUBLIC
    Code:
      stack=3, locals=1, args_size=1
         0: new           #17                 // class java/lang/Error
         3: dup
         4: ldc           #47                 // String Unresolved compilation problem: \n\tThe method getDescription() of type NativeMPFRSparseLinearAlgebraBackend<E> must override or implement a supertype method\n
         6: invokespecial #21                 // Method java/lang/Error."<init>":(Ljava/lang/String;)V
         9: athrow
      LineNumberTable:
        line 60: 0
      LocalVariableTable:
        Start  Length  Slot  Name   Signature
            0      10     0  this   Lorg/episteme/nativ/mathematics/linearalgebra/backends/NativeMPFRSparseLinearAlgebraBackend;
      LocalVariableTypeTable:
        Start  Length  Slot  Name   Signature
            0      10     0  this   Lorg/episteme/nativ/mathematics/linearalgebra/backends/NativeMPFRSparseLinearAlgebraBackend<TE;>;

  public java.lang.String getType();
    descriptor: ()Ljava/lang/String;
    flags: (0x0001) ACC_PUBLIC
    Code:
      stack=3, locals=1, args_size=1
         0: new           #17                 // class java/lang/Error
         3: dup
         4: ldc           #50                 // String Unresolved compilation problem: \n\tThe method getType() of type NativeMPFRSparseLinearAlgebraBackend<E> must override or implement a supertype method\n
         6: invokespecial #21                 // Method java/lang/Error."<init>":(Ljava/lang/String;)V
         9: athrow
      LineNumberTable:
        line 61: 0
      LocalVariableTable:
        Start  Length  Slot  Name   Signature
            0      10     0  this   Lorg/episteme/nativ/mathematics/linearalgebra/backends/NativeMPFRSparseLinearAlgebraBackend;
      LocalVariableTypeTable:
        Start  Length  Slot  Name   Signature
            0      10     0  this   Lorg/episteme/nativ/mathematics/linearalgebra/backends/NativeMPFRSparseLinearAlgebraBackend<TE;>;

  public int getPriority();
    descriptor: ()I
    flags: (0x0001) ACC_PUBLIC
    Code:
      stack=3, locals=1, args_size=1
         0: new           #17                 // class java/lang/Error
         3: dup
         4: ldc           #54                 // String Unresolved compilation problem: \n\tThe method getPriority() of type NativeMPFRSparseLinearAlgebraBackend<E> must override or implement a supertype method\n
         6: invokespecial #21                 // Method java/lang/Error."<init>":(Ljava/lang/String;)V
         9: athrow
      LineNumberTable:
        line 62: 0
      LocalVariableTable:
        Start  Length  Slot  Name   Signature
            0      10     0  this   Lorg/episteme/nativ/mathematics/linearalgebra/backends/NativeMPFRSparseLinearAlgebraBackend;
      LocalVariableTypeTable:
        Start  Length  Slot  Name   Signature
            0      10     0  this   Lorg/episteme/nativ/mathematics/linearalgebra/backends/NativeMPFRSparseLinearAlgebraBackend<TE;>;

  public org.episteme.core.technical.backend.HardwareAccelerator getAcceleratorType();
    descriptor: ()Lorg/episteme/core/technical/backend/HardwareAccelerator;
    flags: (0x0001) ACC_PUBLIC
    Code:
      stack=3, locals=1, args_size=1
         0: new           #17                 // class java/lang/Error
         3: dup
         4: ldc           #58                 // String Unresolved compilation problem: \n\torg.episteme.core cannot be resolved to a type\n
         6: invokespecial #21                 // Method java/lang/Error."<init>":(Ljava/lang/String;)V
         9: athrow
      LineNumberTable:
        line 63: 0
      LocalVariableTable:
        Start  Length  Slot  Name   Signature
            0      10     0  this   Lorg/episteme/nativ/mathematics/linearalgebra/backends/NativeMPFRSparseLinearAlgebraBackend;
      LocalVariableTypeTable:
        Start  Length  Slot  Name   Signature
            0      10     0  this   Lorg/episteme/nativ/mathematics/linearalgebra/backends/NativeMPFRSparseLinearAlgebraBackend<TE;>;

  public boolean isLoaded();
    descriptor: ()Z
    flags: (0x0001) ACC_PUBLIC
    Code:
      stack=3, locals=1, args_size=1
         0: new           #17                 // class java/lang/Error
         3: dup
         4: ldc           #31                 // String Unresolved compilation problem: \n
         6: invokespecial #21                 // Method java/lang/Error."<init>":(Ljava/lang/String;)V
         9: athrow
      LineNumberTable:
        line 64: 0
      LocalVariableTable:
        Start  Length  Slot  Name   Signature
            0      10     0  this   Lorg/episteme/nativ/mathematics/linearalgebra/backends/NativeMPFRSparseLinearAlgebraBackend;
      LocalVariableTypeTable:
        Start  Length  Slot  Name   Signature
            0      10     0  this   Lorg/episteme/nativ/mathematics/linearalgebra/backends/NativeMPFRSparseLinearAlgebraBackend<TE;>;

  public java.lang.String getNativeLibraryName();
    descriptor: ()Ljava/lang/String;
    flags: (0x0001) ACC_PUBLIC
    Code:
      stack=3, locals=1, args_size=1
         0: new           #17                 // class java/lang/Error
         3: dup
         4: ldc           #31                 // String Unresolved compilation problem: \n
         6: invokespecial #21                 // Method java/lang/Error."<init>":(Ljava/lang/String;)V
         9: athrow
      LineNumberTable:
        line 65: 0
      LocalVariableTable:
        Start  Length  Slot  Name   Signature
            0      10     0  this   Lorg/episteme/nativ/mathematics/linearalgebra/backends/NativeMPFRSparseLinearAlgebraBackend;
      LocalVariableTypeTable:
        Start  Length  Slot  Name   Signature
            0      10     0  this   Lorg/episteme/nativ/mathematics/linearalgebra/backends/NativeMPFRSparseLinearAlgebraBackend<TE;>;

  public java.lang.Object createBackend();
    descriptor: ()Ljava/lang/Object;
    flags: (0x0001) ACC_PUBLIC
    Code:
      stack=3, locals=1, args_size=1
         0: new           #17                 // class java/lang/Error
         3: dup
         4: ldc           #64                 // String Unresolved compilation problem: \n\tThe method createBackend() of type NativeMPFRSparseLinearAlgebraBackend<E> must override or implement a supertype method\n
         6: invokespecial #21                 // Method java/lang/Error."<init>":(Ljava/lang/String;)V
         9: athrow
      LineNumberTable:
        line 66: 0
      LocalVariableTable:
        Start  Length  Slot  Name   Signature
            0      10     0  this   Lorg/episteme/nativ/mathematics/linearalgebra/backends/NativeMPFRSparseLinearAlgebraBackend;
      LocalVariableTypeTable:
        Start  Length  Slot  Name   Signature
            0      10     0  this   Lorg/episteme/nativ/mathematics/linearalgebra/backends/NativeMPFRSparseLinearAlgebraBackend<TE;>;

  public org.episteme.core.technical.backend.ExecutionContext createContext();
    descriptor: ()Lorg/episteme/core/technical/backend/ExecutionContext;
    flags: (0x0001) ACC_PUBLIC
    Code:
      stack=3, locals=1, args_size=1
         0: new           #17                 // class java/lang/Error
         3: dup
         4: ldc           #68                 // String Unresolved compilation problems: \n\torg.episteme.core cannot be resolved to a type\n\torg.episteme.core cannot be resolved to a type\n\tThe method close() of type new ExecutionContext(){} must override or implement a supertype method\n
         6: invokespecial #21                 // Method java/lang/Error."<init>":(Ljava/lang/String;)V
         9: athrow
      LineNumberTable:
        line 67: 0
      LocalVariableTable:
        Start  Length  Slot  Name   Signature
            0      10     0  this   Lorg/episteme/nativ/mathematics/linearalgebra/backends/NativeMPFRSparseLinearAlgebraBackend;
      LocalVariableTypeTable:
        Start  Length  Slot  Name   Signature
            0      10     0  this   Lorg/episteme/nativ/mathematics/linearalgebra/backends/NativeMPFRSparseLinearAlgebraBackend<TE;>;

  public boolean isExplicitlyDisabled();
    descriptor: ()Z
    flags: (0x0001) ACC_PUBLIC
    Code:
      stack=3, locals=1, args_size=1
         0: new           #17                 // class java/lang/Error
         3: dup
         4: ldc           #71                 // String Unresolved compilation problem: \n\tThe method isExplicitlyDisabled() of type NativeMPFRSparseLinearAlgebraBackend<E> must override or implement a supertype method\n
         6: invokespecial #21                 // Method java/lang/Error."<init>":(Ljava/lang/String;)V
         9: athrow
      LineNumberTable:
        line 77: 0
      LocalVariableTable:
        Start  Length  Slot  Name   Signature
            0      10     0  this   Lorg/episteme/nativ/mathematics/linearalgebra/backends/NativeMPFRSparseLinearAlgebraBackend;
      LocalVariableTypeTable:
        Start  Length  Slot  Name   Signature
            0      10     0  this   Lorg/episteme/nativ/mathematics/linearalgebra/backends/NativeMPFRSparseLinearAlgebraBackend<TE;>;

  public void shutdown();
    descriptor: ()V
    flags: (0x0001) ACC_PUBLIC
    Code:
      stack=3, locals=1, args_size=1
         0: new           #17                 // class java/lang/Error
         3: dup
         4: ldc           #74                 // String Unresolved compilation problem: \n\tThe method shutdown() of type NativeMPFRSparseLinearAlgebraBackend<E> must override or implement a supertype method\n
         6: invokespecial #21                 // Method java/lang/Error."<init>":(Ljava/lang/String;)V
         9: athrow
      LineNumberTable:
        line 84: 0
      LocalVariableTable:
        Start  Length  Slot  Name   Signature
            0      10     0  this   Lorg/episteme/nativ/mathematics/linearalgebra/backends/NativeMPFRSparseLinearAlgebraBackend;
      LocalVariableTypeTable:
        Start  Length  Slot  Name   Signature
            0      10     0  this   Lorg/episteme/nativ/mathematics/linearalgebra/backends/NativeMPFRSparseLinearAlgebraBackend<TE;>;

  public java.util.Map<java.lang.String, java.lang.String> getMetadata();
    descriptor: ()Ljava/util/Map;
    flags: (0x0001) ACC_PUBLIC
    Signature: #79                          // ()Ljava/util/Map<Ljava/lang/String;Ljava/lang/String;>;
    Code:
      stack=3, locals=1, args_size=1
         0: new           #17                 // class java/lang/Error
         3: dup
         4: ldc           #80                 // String Unresolved compilation problem: \n\tThe method getMetadata() of type NativeMPFRSparseLinearAlgebraBackend<E> must override or implement a supertype method\n
         6: invokespecial #21                 // Method java/lang/Error."<init>":(Ljava/lang/String;)V
         9: athrow
      LineNumberTable:
        line 85: 0
      LocalVariableTable:
        Start  Length  Slot  Name   Signature
            0      10     0  this   Lorg/episteme/nativ/mathematics/linearalgebra/backends/NativeMPFRSparseLinearAlgebraBackend;
      LocalVariableTypeTable:
        Start  Length  Slot  Name   Signature
            0      10     0  this   Lorg/episteme/nativ/mathematics/linearalgebra/backends/NativeMPFRSparseLinearAlgebraBackend<TE;>;

  public double score(org.episteme.core.technical.algorithm.OperationContext);
    descriptor: (Lorg/episteme/core/technical/algorithm/OperationContext;)D
    flags: (0x0001) ACC_PUBLIC
    Code:
      stack=3, locals=2, args_size=2
         0: new           #17                 // class java/lang/Error
         3: dup
         4: ldc           #58                 // String Unresolved compilation problem: \n\torg.episteme.core cannot be resolved to a type\n
         6: invokespecial #21                 // Method java/lang/Error."<init>":(Ljava/lang/String;)V
         9: athrow
      LineNumberTable:
        line 100: 0
      LocalVariableTable:
        Start  Length  Slot  Name   Signature
            0      10     0  this   Lorg/episteme/nativ/mathematics/linearalgebra/backends/NativeMPFRSparseLinearAlgebraBackend;
      LocalVariableTypeTable:
        Start  Length  Slot  Name   Signature
            0      10     0  this   Lorg/episteme/nativ/mathematics/linearalgebra/backends/NativeMPFRSparseLinearAlgebraBackend<TE;>;

  private long getPrecision();
    descriptor: ()J
    flags: (0x0002) ACC_PRIVATE
    Code:
      stack=3, locals=1, args_size=1
         0: new           #17                 // class java/lang/Error
         3: dup
         4: ldc           #86                 // String Unresolved compilation problem: \n\torg.episteme.core.mathematics.context cannot be resolved\n
         6: invokespecial #21                 // Method java/lang/Error."<init>":(Ljava/lang/String;)V
         9: athrow
      LineNumberTable:
        line 110: 0
      LocalVariableTable:
        Start  Length  Slot  Name   Signature
            0      10     0  this   Lorg/episteme/nativ/mathematics/linearalgebra/backends/NativeMPFRSparseLinearAlgebraBackend;
      LocalVariableTypeTable:
        Start  Length  Slot  Name   Signature
            0      10     0  this   Lorg/episteme/nativ/mathematics/linearalgebra/backends/NativeMPFRSparseLinearAlgebraBackend<TE;>;

  public E trace(Matrix<E>);
    descriptor: (LMatrix;)Ljava/lang/Object;
    flags: (0x0001) ACC_PUBLIC
    Signature: #90                          // (LMatrix<TE;>;)TE;
    Code:
      stack=3, locals=2, args_size=2
         0: new           #17                 // class java/lang/Error
         3: dup
         4: ldc           #91                 // String Unresolved compilation problem: \n\tMatrix cannot be resolved to a type\n
         6: invokespecial #21                 // Method java/lang/Error."<init>":(Ljava/lang/String;)V
         9: athrow
      LineNumberTable:
        line 115: 0
      LocalVariableTable:
        Start  Length  Slot  Name   Signature
            0      10     0  this   Lorg/episteme/nativ/mathematics/linearalgebra/backends/NativeMPFRSparseLinearAlgebraBackend;
      LocalVariableTypeTable:
        Start  Length  Slot  Name   Signature
            0      10     0  this   Lorg/episteme/nativ/mathematics/linearalgebra/backends/NativeMPFRSparseLinearAlgebraBackend<TE;>;

  private static void track(org.episteme.nativ.technical.backend.nativ.ResourceTracker, java.lang.foreign.MemorySegment);
    descriptor: (Lorg/episteme/nativ/technical/backend/nativ/ResourceTracker;Ljava/lang/foreign/MemorySegment;)V
    flags: (0x000a) ACC_PRIVATE, ACC_STATIC
    Code:
      stack=3, locals=2, args_size=2
         0: new           #17                 // class java/lang/Error
         3: dup
         4: ldc           #31                 // String Unresolved compilation problem: \n
         6: invokespecial #21                 // Method java/lang/Error."<init>":(Ljava/lang/String;)V
         9: athrow
      LineNumberTable:
        line 176: 0
      LocalVariableTable:
        Start  Length  Slot  Name   Signature

  private static void trackArray(org.episteme.nativ.technical.backend.nativ.ResourceTracker, java.lang.foreign.MemorySegment, int);
    descriptor: (Lorg/episteme/nativ/technical/backend/nativ/ResourceTracker;Ljava/lang/foreign/MemorySegment;I)V
    flags: (0x000a) ACC_PRIVATE, ACC_STATIC
    Code:
      stack=3, locals=3, args_size=3
         0: new           #17                 // class java/lang/Error
         3: dup
         4: ldc           #31                 // String Unresolved compilation problem: \n
         6: invokespecial #21                 // Method java/lang/Error."<init>":(Ljava/lang/String;)V
         9: athrow
      LineNumberTable:
        line 190: 0
      LocalVariableTable:
        Start  Length  Slot  Name   Signature

  private Real readMPFR(java.lang.foreign.MemorySegment, java.lang.foreign.Arena);
    descriptor: (Ljava/lang/foreign/MemorySegment;Ljava/lang/foreign/Arena;)LReal;
    flags: (0x0002) ACC_PRIVATE
    Code:
      stack=3, locals=3, args_size=3
         0: new           #17                 // class java/lang/Error
         3: dup
         4: ldc           #99                 // String Unresolved compilation problem: \n\tReal cannot be resolved to a type\n
         6: invokespecial #21                 // Method java/lang/Error."<init>":(Ljava/lang/String;)V
         9: athrow
      LineNumberTable:
        line 208: 0
      LocalVariableTable:
        Start  Length  Slot  Name   Signature
            0      10     0  this   Lorg/episteme/nativ/mathematics/linearalgebra/backends/NativeMPFRSparseLinearAlgebraBackend;
      LocalVariableTypeTable:
        Start  Length  Slot  Name   Signature
            0      10     0  this   Lorg/episteme/nativ/mathematics/linearalgebra/backends/NativeMPFRSparseLinearAlgebraBackend<TE;>;

  private void setMPFR_internal(java.lang.foreign.MemorySegment, java.lang.foreign.MemorySegment, java.lang.Object, java.lang.foreign.Arena) throws java.lang.Throwable;
    descriptor: (Ljava/lang/foreign/MemorySegment;Ljava/lang/foreign/MemorySegment;Ljava/lang/Object;Ljava/lang/foreign/Arena;)V
    flags: (0x0002) ACC_PRIVATE
    Exceptions:
      throws java.lang.Throwable
    Code:
      stack=3, locals=5, args_size=5
         0: new           #17                 // class java/lang/Error
         3: dup
         4: ldc           #106                // String Unresolved compilation problem: \n\tThe method getRealPart(Object) from the type NativeMPFRSparseLinearAlgebraBackend<E> refers to the missing type Real\n
         6: invokespecial #21                 // Method java/lang/Error."<init>":(Ljava/lang/String;)V
         9: athrow
      LineNumberTable:
        line 219: 0
      LocalVariableTable:
        Start  Length  Slot  Name   Signature
            0      10     0  this   Lorg/episteme/nativ/mathematics/linearalgebra/backends/NativeMPFRSparseLinearAlgebraBackend;
      LocalVariableTypeTable:
        Start  Length  Slot  Name   Signature
            0      10     0  this   Lorg/episteme/nativ/mathematics/linearalgebra/backends/NativeMPFRSparseLinearAlgebraBackend<TE;>;

  private boolean isComplex(java.lang.Object);
    descriptor: (Ljava/lang/Object;)Z
    flags: (0x0002) ACC_PRIVATE
    Code:
      stack=3, locals=2, args_size=2
         0: new           #17                 // class java/lang/Error
         3: dup
         4: ldc           #91                 // String Unresolved compilation problem: \n\tMatrix cannot be resolved to a type\n
         6: invokespecial #21                 // Method java/lang/Error."<init>":(Ljava/lang/String;)V
         9: athrow
      LineNumberTable:
        line 235: 0
      LocalVariableTable:
        Start  Length  Slot  Name   Signature
            0      10     0  this   Lorg/episteme/nativ/mathematics/linearalgebra/backends/NativeMPFRSparseLinearAlgebraBackend;
      LocalVariableTypeTable:
        Start  Length  Slot  Name   Signature
            0      10     0  this   Lorg/episteme/nativ/mathematics/linearalgebra/backends/NativeMPFRSparseLinearAlgebraBackend<TE;>;

  boolean isComplexRing(Ring<?>);
    descriptor: (LRing;)Z
    flags: (0x0000)
    Signature: #112                         // (LRing<*>;)Z
    Code:
      stack=3, locals=2, args_size=2
         0: new           #17                 // class java/lang/Error
         3: dup
         4: ldc           #113                // String Unresolved compilation problem: \n\tRing cannot be resolved to a type\n
         6: invokespecial #21                 // Method java/lang/Error."<init>":(Ljava/lang/String;)V
         9: athrow
      LineNumberTable:
        line 240: 0
      LocalVariableTable:
        Start  Length  Slot  Name   Signature
            0      10     0  this   Lorg/episteme/nativ/mathematics/linearalgebra/backends/NativeMPFRSparseLinearAlgebraBackend;
      LocalVariableTypeTable:
        Start  Length  Slot  Name   Signature
            0      10     0  this   Lorg/episteme/nativ/mathematics/linearalgebra/backends/NativeMPFRSparseLinearAlgebraBackend<TE;>;

  E castScalar(java.lang.Object, Ring<E>);
    descriptor: (Ljava/lang/Object;LRing;)Ljava/lang/Object;
    flags: (0x0000)
    Signature: #117                         // (Ljava/lang/Object;LRing<TE;>;)TE;
    Code:
      stack=3, locals=3, args_size=3
         0: new           #17                 // class java/lang/Error
         3: dup
         4: ldc           #113                // String Unresolved compilation problem: \n\tRing cannot be resolved to a type\n
         6: invokespecial #21                 // Method java/lang/Error."<init>":(Ljava/lang/String;)V
         9: athrow
      LineNumberTable:
        line 246: 0
      LocalVariableTable:
        Start  Length  Slot  Name   Signature
            0      10     0  this   Lorg/episteme/nativ/mathematics/linearalgebra/backends/NativeMPFRSparseLinearAlgebraBackend;
      LocalVariableTypeTable:
        Start  Length  Slot  Name   Signature
            0      10     0  this   Lorg/episteme/nativ/mathematics/linearalgebra/backends/NativeMPFRSparseLinearAlgebraBackend<TE;>;

  boolean isZero(java.lang.Object, Ring<?>);
    descriptor: (Ljava/lang/Object;LRing;)Z
    flags: (0x0000)
    Signature: #120                         // (Ljava/lang/Object;LRing<*>;)Z
    Code:
      stack=3, locals=3, args_size=3
         0: new           #17                 // class java/lang/Error
         3: dup
         4: ldc           #113                // String Unresolved compilation problem: \n\tRing cannot be resolved to a type\n
         6: invokespecial #21                 // Method java/lang/Error."<init>":(Ljava/lang/String;)V
         9: athrow
      LineNumberTable:
        line 284: 0
      LocalVariableTable:
        Start  Length  Slot  Name   Signature
            0      10     0  this   Lorg/episteme/nativ/mathematics/linearalgebra/backends/NativeMPFRSparseLinearAlgebraBackend;
      LocalVariableTypeTable:
        Start  Length  Slot  Name   Signature
            0      10     0  this   Lorg/episteme/nativ/mathematics/linearalgebra/backends/NativeMPFRSparseLinearAlgebraBackend<TE;>;

  private double getRealValue(java.lang.Object);
    descriptor: (Ljava/lang/Object;)D
    flags: (0x0002) ACC_PRIVATE
    Code:
      stack=3, locals=2, args_size=2
         0: new           #17                 // class java/lang/Error
         3: dup
         4: ldc           #99                 // String Unresolved compilation problem: \n\tReal cannot be resolved to a type\n
         6: invokespecial #21                 // Method java/lang/Error."<init>":(Ljava/lang/String;)V
         9: athrow
      LineNumberTable:
        line 303: 0
      LocalVariableTable:
        Start  Length  Slot  Name   Signature
            0      10     0  this   Lorg/episteme/nativ/mathematics/linearalgebra/backends/NativeMPFRSparseLinearAlgebraBackend;
      LocalVariableTypeTable:
        Start  Length  Slot  Name   Signature
            0      10     0  this   Lorg/episteme/nativ/mathematics/linearalgebra/backends/NativeMPFRSparseLinearAlgebraBackend<TE;>;

  private Real getReal(java.lang.Object);
    descriptor: (Ljava/lang/Object;)LReal;
    flags: (0x0002) ACC_PRIVATE
    Code:
      stack=3, locals=2, args_size=2
         0: new           #17                 // class java/lang/Error
         3: dup
         4: ldc           #99                 // String Unresolved compilation problem: \n\tReal cannot be resolved to a type\n
         6: invokespecial #21                 // Method java/lang/Error."<init>":(Ljava/lang/String;)V
         9: athrow
      LineNumberTable:
        line 308: 0
      LocalVariableTable:
        Start  Length  Slot  Name   Signature
            0      10     0  this   Lorg/episteme/nativ/mathematics/linearalgebra/backends/NativeMPFRSparseLinearAlgebraBackend;
      LocalVariableTypeTable:
        Start  Length  Slot  Name   Signature
            0      10     0  this   Lorg/episteme/nativ/mathematics/linearalgebra/backends/NativeMPFRSparseLinearAlgebraBackend<TE;>;

  private void setMPFR(java.lang.foreign.MemorySegment, E, java.lang.foreign.Arena) throws java.lang.Throwable;
    descriptor: (Ljava/lang/foreign/MemorySegment;Ljava/lang/Object;Ljava/lang/foreign/Arena;)V
    flags: (0x0002) ACC_PRIVATE
    Exceptions:
      throws java.lang.Throwable
    Signature: #127                         // (Ljava/lang/foreign/MemorySegment;TE;Ljava/lang/foreign/Arena;)V
    Code:
      stack=3, locals=4, args_size=4
         0: new           #17                 // class java/lang/Error
         3: dup
         4: ldc           #31                 // String Unresolved compilation problem: \n
         6: invokespecial #21                 // Method java/lang/Error."<init>":(Ljava/lang/String;)V
         9: athrow
      LineNumberTable:
        line 316: 0
      LocalVariableTable:
        Start  Length  Slot  Name   Signature
            0      10     0  this   Lorg/episteme/nativ/mathematics/linearalgebra/backends/NativeMPFRSparseLinearAlgebraBackend;
      LocalVariableTypeTable:
        Start  Length  Slot  Name   Signature
            0      10     0  this   Lorg/episteme/nativ/mathematics/linearalgebra/backends/NativeMPFRSparseLinearAlgebraBackend<TE;>;

  java.lang.foreign.MemorySegment initVector(Matrix<E>, java.lang.foreign.Arena, org.episteme.nativ.technical.backend.nativ.ResourceTracker, long, boolean) throws java.lang.Throwable;
    descriptor: (LMatrix;Ljava/lang/foreign/Arena;Lorg/episteme/nativ/technical/backend/nativ/ResourceTracker;JZ)Ljava/lang/foreign/MemorySegment;
    flags: (0x0000)
    Exceptions:
      throws java.lang.Throwable
    Signature: #130                         // (LMatrix<TE;>;Ljava/lang/foreign/Arena;Lorg/episteme/nativ/technical/backend/nativ/ResourceTracker;JZ)Ljava/lang/foreign/MemorySegment;
    Code:
      stack=3, locals=7, args_size=6
         0: new           #17                 // class java/lang/Error
         3: dup
         4: ldc           #91                 // String Unresolved compilation problem: \n\tMatrix cannot be resolved to a type\n
         6: invokespecial #21                 // Method java/lang/Error."<init>":(Ljava/lang/String;)V
         9: athrow
      LineNumberTable:
        line 321: 0
      LocalVariableTable:
        Start  Length  Slot  Name   Signature
            0      10     0  this   Lorg/episteme/nativ/mathematics/linearalgebra/backends/NativeMPFRSparseLinearAlgebraBackend;
      LocalVariableTypeTable:
        Start  Length  Slot  Name   Signature
            0      10     0  this   Lorg/episteme/nativ/mathematics/linearalgebra/backends/NativeMPFRSparseLinearAlgebraBackend<TE;>;

  private Real getRealPart(java.lang.Object);
    descriptor: (Ljava/lang/Object;)LReal;
    flags: (0x0002) ACC_PRIVATE
    Code:
      stack=3, locals=2, args_size=2
         0: new           #17                 // class java/lang/Error
         3: dup
         4: ldc           #99                 // String Unresolved compilation problem: \n\tReal cannot be resolved to a type\n
         6: invokespecial #21                 // Method java/lang/Error."<init>":(Ljava/lang/String;)V
         9: athrow
      LineNumberTable:
        line 370: 0
      LocalVariableTable:
        Start  Length  Slot  Name   Signature
            0      10     0  this   Lorg/episteme/nativ/mathematics/linearalgebra/backends/NativeMPFRSparseLinearAlgebraBackend;
      LocalVariableTypeTable:
        Start  Length  Slot  Name   Signature
            0      10     0  this   Lorg/episteme/nativ/mathematics/linearalgebra/backends/NativeMPFRSparseLinearAlgebraBackend<TE;>;

  private Real getImagPart(java.lang.Object);
    descriptor: (Ljava/lang/Object;)LReal;
    flags: (0x0002) ACC_PRIVATE
    Code:
      stack=3, locals=2, args_size=2
         0: new           #17                 // class java/lang/Error
         3: dup
         4: ldc           #99                 // String Unresolved compilation problem: \n\tReal cannot be resolved to a type\n
         6: invokespecial #21                 // Method java/lang/Error."<init>":(Ljava/lang/String;)V
         9: athrow
      LineNumberTable:
        line 377: 0
      LocalVariableTable:
        Start  Length  Slot  Name   Signature
            0      10     0  this   Lorg/episteme/nativ/mathematics/linearalgebra/backends/NativeMPFRSparseLinearAlgebraBackend;
      LocalVariableTypeTable:
        Start  Length  Slot  Name   Signature
            0      10     0  this   Lorg/episteme/nativ/mathematics/linearalgebra/backends/NativeMPFRSparseLinearAlgebraBackend<TE;>;

  private void dotProduct(java.lang.foreign.MemorySegment, java.lang.foreign.MemorySegment, int, java.lang.foreign.MemorySegment, long, java.lang.foreign.Arena, boolean) throws java.lang.Throwable;
    descriptor: (Ljava/lang/foreign/MemorySegment;Ljava/lang/foreign/MemorySegment;ILjava/lang/foreign/MemorySegment;JLjava/lang/foreign/Arena;Z)V
    flags: (0x0002) ACC_PRIVATE
    Exceptions:
      throws java.lang.Throwable
    Code:
      stack=3, locals=9, args_size=8
         0: new           #17                 // class java/lang/Error
         3: dup
         4: ldc           #31                 // String Unresolved compilation problem: \n
         6: invokespecial #21                 // Method java/lang/Error."<init>":(Ljava/lang/String;)V
         9: athrow
      LineNumberTable:
        line 382: 0
      LocalVariableTable:
        Start  Length  Slot  Name   Signature
            0      10     0  this   Lorg/episteme/nativ/mathematics/linearalgebra/backends/NativeMPFRSparseLinearAlgebraBackend;
      LocalVariableTypeTable:
        Start  Length  Slot  Name   Signature
            0      10     0  this   Lorg/episteme/nativ/mathematics/linearalgebra/backends/NativeMPFRSparseLinearAlgebraBackend<TE;>;

  public Vector<E> multiply(Matrix<E>, Vector<E>);
    descriptor: (LMatrix;LVector;)LVector;
    flags: (0x0001) ACC_PUBLIC
    Signature: #137                         // (LMatrix<TE;>;LVector<TE;>;)LVector<TE;>;
    Code:
      stack=3, locals=3, args_size=3
         0: new           #17                 // class java/lang/Error
         3: dup
         4: ldc           #91                 // String Unresolved compilation problem: \n\tMatrix cannot be resolved to a type\n
         6: invokespecial #21                 // Method java/lang/Error."<init>":(Ljava/lang/String;)V
         9: athrow
      LineNumberTable:
        line 428: 0
      LocalVariableTable:
        Start  Length  Slot  Name   Signature
            0      10     0  this   Lorg/episteme/nativ/mathematics/linearalgebra/backends/NativeMPFRSparseLinearAlgebraBackend;
      LocalVariableTypeTable:
        Start  Length  Slot  Name   Signature
            0      10     0  this   Lorg/episteme/nativ/mathematics/linearalgebra/backends/NativeMPFRSparseLinearAlgebraBackend<TE;>;

  private void axpy_internal(java.lang.foreign.MemorySegment, E, java.lang.foreign.MemorySegment, int, long, java.lang.foreign.Arena, org.episteme.nativ.technical.backend.nativ.ResourceTracker, boolean) throws java.lang.Throwable;
    descriptor: (Ljava/lang/foreign/MemorySegment;Ljava/lang/Object;Ljava/lang/foreign/MemorySegment;IJLjava/lang/foreign/Arena;Lorg/episteme/nativ/technical/backend/nativ/ResourceTracker;Z)V
    flags: (0x0002) ACC_PRIVATE
    Exceptions:
      throws java.lang.Throwable
    Signature: #140                         // (Ljava/lang/foreign/MemorySegment;TE;Ljava/lang/foreign/MemorySegment;IJLjava/lang/foreign/Arena;Lorg/episteme/nativ/technical/backend/nativ/ResourceTracker;Z)V
    Code:
      stack=3, locals=10, args_size=9
         0: new           #17                 // class java/lang/Error
         3: dup
         4: ldc           #141                // String Unresolved compilation problem: \n\tComplex cannot be resolved to a type\n
         6: invokespecial #21                 // Method java/lang/Error."<init>":(Ljava/lang/String;)V
         9: athrow
      LineNumberTable:
        line 481: 0
      LocalVariableTable:
        Start  Length  Slot  Name   Signature
            0      10     0  this   Lorg/episteme/nativ/mathematics/linearalgebra/backends/NativeMPFRSparseLinearAlgebraBackend;
      LocalVariableTypeTable:
        Start  Length  Slot  Name   Signature
            0      10     0  this   Lorg/episteme/nativ/mathematics/linearalgebra/backends/NativeMPFRSparseLinearAlgebraBackend<TE;>;

  E dot_internal(java.lang.foreign.MemorySegment, java.lang.foreign.MemorySegment, int, long, java.lang.foreign.Arena, org.episteme.nativ.technical.backend.nativ.ResourceTracker, boolean, Ring<E>) throws java.lang.Throwable;
    descriptor: (Ljava/lang/foreign/MemorySegment;Ljava/lang/foreign/MemorySegment;IJLjava/lang/foreign/Arena;Lorg/episteme/nativ/technical/backend/nativ/ResourceTracker;ZLRing;)Ljava/lang/Object;
    flags: (0x0000)
    Exceptions:
      throws java.lang.Throwable
    Signature: #145                         // (Ljava/lang/foreign/MemorySegment;Ljava/lang/foreign/MemorySegment;IJLjava/lang/foreign/Arena;Lorg/episteme/nativ/technical/backend/nativ/ResourceTracker;ZLRing<TE;>;)TE;
    Code:
      stack=3, locals=10, args_size=9
         0: new           #17                 // class java/lang/Error
         3: dup
         4: ldc           #113                // String Unresolved compilation problem: \n\tRing cannot be resolved to a type\n
         6: invokespecial #21                 // Method java/lang/Error."<init>":(Ljava/lang/String;)V
         9: athrow
      LineNumberTable:
        line 516: 0
      LocalVariableTable:
        Start  Length  Slot  Name   Signature
            0      10     0  this   Lorg/episteme/nativ/mathematics/linearalgebra/backends/NativeMPFRSparseLinearAlgebraBackend;
      LocalVariableTypeTable:
        Start  Length  Slot  Name   Signature
            0      10     0  this   Lorg/episteme/nativ/mathematics/linearalgebra/backends/NativeMPFRSparseLinearAlgebraBackend<TE;>;

  E norm_internal(java.lang.foreign.MemorySegment, int, long, java.lang.foreign.Arena, org.episteme.nativ.technical.backend.nativ.ResourceTracker, boolean, Ring<E>) throws java.lang.Throwable;
    descriptor: (Ljava/lang/foreign/MemorySegment;IJLjava/lang/foreign/Arena;Lorg/episteme/nativ/technical/backend/nativ/ResourceTracker;ZLRing;)Ljava/lang/Object;
    flags: (0x0000)
    Exceptions:
      throws java.lang.Throwable
    Signature: #148                         // (Ljava/lang/foreign/MemorySegment;IJLjava/lang/foreign/Arena;Lorg/episteme/nativ/technical/backend/nativ/ResourceTracker;ZLRing<TE;>;)TE;
    Code:
      stack=3, locals=9, args_size=8
         0: new           #17                 // class java/lang/Error
         3: dup
         4: ldc           #113                // String Unresolved compilation problem: \n\tRing cannot be resolved to a type\n
         6: invokespecial #21                 // Method java/lang/Error."<init>":(Ljava/lang/String;)V
         9: athrow
      LineNumberTable:
        line 574: 0
      LocalVariableTable:
        Start  Length  Slot  Name   Signature
            0      10     0  this   Lorg/episteme/nativ/mathematics/linearalgebra/backends/NativeMPFRSparseLinearAlgebraBackend;
      LocalVariableTypeTable:
        Start  Length  Slot  Name   Signature
            0      10     0  this   Lorg/episteme/nativ/mathematics/linearalgebra/backends/NativeMPFRSparseLinearAlgebraBackend<TE;>;

  private void copy_internal(java.lang.foreign.MemorySegment, java.lang.foreign.MemorySegment, int, boolean) throws java.lang.Throwable;
    descriptor: (Ljava/lang/foreign/MemorySegment;Ljava/lang/foreign/MemorySegment;IZ)V
    flags: (0x0002) ACC_PRIVATE
    Exceptions:
      throws java.lang.Throwable
    Code:
      stack=3, locals=5, args_size=5
         0: new           #17                 // class java/lang/Error
         3: dup
         4: ldc           #31                 // String Unresolved compilation problem: \n
         6: invokespecial #21                 // Method java/lang/Error."<init>":(Ljava/lang/String;)V
         9: athrow
      LineNumberTable:
        line 597: 0
      LocalVariableTable:
        Start  Length  Slot  Name   Signature
            0      10     0  this   Lorg/episteme/nativ/mathematics/linearalgebra/backends/NativeMPFRSparseLinearAlgebraBackend;
      LocalVariableTypeTable:
        Start  Length  Slot  Name   Signature
            0      10     0  this   Lorg/episteme/nativ/mathematics/linearalgebra/backends/NativeMPFRSparseLinearAlgebraBackend<TE;>;

  private void scale_internal(java.lang.foreign.MemorySegment, E, int, long, java.lang.foreign.Arena, org.episteme.nativ.technical.backend.nativ.ResourceTracker, boolean) throws java.lang.Throwable;
    descriptor: (Ljava/lang/foreign/MemorySegment;Ljava/lang/Object;IJLjava/lang/foreign/Arena;Lorg/episteme/nativ/technical/backend/nativ/ResourceTracker;Z)V
    flags: (0x0002) ACC_PRIVATE
    Exceptions:
      throws java.lang.Throwable
    Signature: #153                         // (Ljava/lang/foreign/MemorySegment;TE;IJLjava/lang/foreign/Arena;Lorg/episteme/nativ/technical/backend/nativ/ResourceTracker;Z)V
    Code:
      stack=3, locals=9, args_size=8
         0: new           #17                 // class java/lang/Error
         3: dup
         4: ldc           #141                // String Unresolved compilation problem: \n\tComplex cannot be resolved to a type\n
         6: invokespecial #21                 // Method java/lang/Error."<init>":(Ljava/lang/String;)V
         9: athrow
      LineNumberTable:
        line 619: 0
      LocalVariableTable:
        Start  Length  Slot  Name   Signature
            0      10     0  this   Lorg/episteme/nativ/mathematics/linearalgebra/backends/NativeMPFRSparseLinearAlgebraBackend;
      LocalVariableTypeTable:
        Start  Length  Slot  Name   Signature
            0      10     0  this   Lorg/episteme/nativ/mathematics/linearalgebra/backends/NativeMPFRSparseLinearAlgebraBackend<TE;>;

  private java.lang.foreign.MemorySegment initNativeValues(java.lang.Object[], long, java.lang.foreign.Arena, org.episteme.nativ.technical.backend.nativ.ResourceTracker, boolean) throws java.lang.Throwable;
    descriptor: ([Ljava/lang/Object;JLjava/lang/foreign/Arena;Lorg/episteme/nativ/technical/backend/nativ/ResourceTracker;Z)Ljava/lang/foreign/MemorySegment;
    flags: (0x0002) ACC_PRIVATE
    Exceptions:
      throws java.lang.Throwable
    Code:
      stack=3, locals=7, args_size=6
         0: new           #17                 // class java/lang/Error
         3: dup
         4: ldc           #31                 // String Unresolved compilation problem: \n
         6: invokespecial #21                 // Method java/lang/Error."<init>":(Ljava/lang/String;)V
         9: athrow
      LineNumberTable:
        line 710: 0
      LocalVariableTable:
        Start  Length  Slot  Name   Signature
            0      10     0  this   Lorg/episteme/nativ/mathematics/linearalgebra/backends/NativeMPFRSparseLinearAlgebraBackend;
      LocalVariableTypeTable:
        Start  Length  Slot  Name   Signature
            0      10     0  this   Lorg/episteme/nativ/mathematics/linearalgebra/backends/NativeMPFRSparseLinearAlgebraBackend<TE;>;

  public Matrix<E> scale(E, Matrix<E>);
    descriptor: (Ljava/lang/Object;LMatrix;)LMatrix;
    flags: (0x0001) ACC_PUBLIC
    Signature: #158                         // (TE;LMatrix<TE;>;)LMatrix<TE;>;
    Code:
      stack=3, locals=3, args_size=3
         0: new           #17                 // class java/lang/Error
         3: dup
         4: ldc           #91                 // String Unresolved compilation problem: \n\tMatrix cannot be resolved to a type\n
         6: invokespecial #21                 // Method java/lang/Error."<init>":(Ljava/lang/String;)V
         9: athrow
      LineNumberTable:
        line 742: 0
      LocalVariableTable:
        Start  Length  Slot  Name   Signature
            0      10     0  this   Lorg/episteme/nativ/mathematics/linearalgebra/backends/NativeMPFRSparseLinearAlgebraBackend;
      LocalVariableTypeTable:
        Start  Length  Slot  Name   Signature
            0      10     0  this   Lorg/episteme/nativ/mathematics/linearalgebra/backends/NativeMPFRSparseLinearAlgebraBackend<TE;>;

  public Vector<E> multiply(Vector<E>, E);
    descriptor: (LVector;Ljava/lang/Object;)LVector;
    flags: (0x0001) ACC_PUBLIC
    Signature: #160                         // (LVector<TE;>;TE;)LVector<TE;>;
    Code:
      stack=3, locals=3, args_size=3
         0: new           #17                 // class java/lang/Error
         3: dup
         4: ldc           #161                // String Unresolved compilation problem: \n\tVector cannot be resolved to a type\n
         6: invokespecial #21                 // Method java/lang/Error."<init>":(Ljava/lang/String;)V
         9: athrow
      LineNumberTable:
        line 835: 0
      LocalVariableTable:
        Start  Length  Slot  Name   Signature
            0      10     0  this   Lorg/episteme/nativ/mathematics/linearalgebra/backends/NativeMPFRSparseLinearAlgebraBackend;
      LocalVariableTypeTable:
        Start  Length  Slot  Name   Signature
            0      10     0  this   Lorg/episteme/nativ/mathematics/linearalgebra/backends/NativeMPFRSparseLinearAlgebraBackend<TE;>;

  public Matrix<E> add(Matrix<E>, Matrix<E>);
    descriptor: (LMatrix;LMatrix;)LMatrix;
    flags: (0x0001) ACC_PUBLIC
    Signature: #165                         // (LMatrix<TE;>;LMatrix<TE;>;)LMatrix<TE;>;
    Code:
      stack=3, locals=3, args_size=3
         0: new           #17                 // class java/lang/Error
         3: dup
         4: ldc           #91                 // String Unresolved compilation problem: \n\tMatrix cannot be resolved to a type\n
         6: invokespecial #21                 // Method java/lang/Error."<init>":(Ljava/lang/String;)V
         9: athrow
      LineNumberTable:
        line 914: 0
      LocalVariableTable:
        Start  Length  Slot  Name   Signature
            0      10     0  this   Lorg/episteme/nativ/mathematics/linearalgebra/backends/NativeMPFRSparseLinearAlgebraBackend;
      LocalVariableTypeTable:
        Start  Length  Slot  Name   Signature
            0      10     0  this   Lorg/episteme/nativ/mathematics/linearalgebra/backends/NativeMPFRSparseLinearAlgebraBackend<TE;>;

  public Vector<E> add(Vector<E>, Vector<E>);
    descriptor: (LVector;LVector;)LVector;
    flags: (0x0001) ACC_PUBLIC
    Signature: #167                         // (LVector<TE;>;LVector<TE;>;)LVector<TE;>;
    Code:
      stack=3, locals=3, args_size=3
         0: new           #17                 // class java/lang/Error
         3: dup
         4: ldc           #161                // String Unresolved compilation problem: \n\tVector cannot be resolved to a type\n
         6: invokespecial #21                 // Method java/lang/Error."<init>":(Ljava/lang/String;)V
         9: athrow
      LineNumberTable:
        line 986: 0
      LocalVariableTable:
        Start  Length  Slot  Name   Signature
            0      10     0  this   Lorg/episteme/nativ/mathematics/linearalgebra/backends/NativeMPFRSparseLinearAlgebraBackend;
      LocalVariableTypeTable:
        Start  Length  Slot  Name   Signature
            0      10     0  this   Lorg/episteme/nativ/mathematics/linearalgebra/backends/NativeMPFRSparseLinearAlgebraBackend<TE;>;

  public Vector<E> subtract(Vector<E>, Vector<E>);
    descriptor: (LVector;LVector;)LVector;
    flags: (0x0001) ACC_PUBLIC
    Signature: #167                         // (LVector<TE;>;LVector<TE;>;)LVector<TE;>;
    Code:
      stack=3, locals=3, args_size=3
         0: new           #17                 // class java/lang/Error
         3: dup
         4: ldc           #161                // String Unresolved compilation problem: \n\tVector cannot be resolved to a type\n
         6: invokespecial #21                 // Method java/lang/Error."<init>":(Ljava/lang/String;)V
         9: athrow
      LineNumberTable:
        line 1038: 0
      LocalVariableTable:
        Start  Length  Slot  Name   Signature
            0      10     0  this   Lorg/episteme/nativ/mathematics/linearalgebra/backends/NativeMPFRSparseLinearAlgebraBackend;
      LocalVariableTypeTable:
        Start  Length  Slot  Name   Signature
            0      10     0  this   Lorg/episteme/nativ/mathematics/linearalgebra/backends/NativeMPFRSparseLinearAlgebraBackend<TE;>;

  public Matrix<E> subtract(Matrix<E>, Matrix<E>);
    descriptor: (LMatrix;LMatrix;)LMatrix;
    flags: (0x0001) ACC_PUBLIC
    Signature: #165                         // (LMatrix<TE;>;LMatrix<TE;>;)LMatrix<TE;>;
    Code:
      stack=3, locals=3, args_size=3
         0: new           #17                 // class java/lang/Error
         3: dup
         4: ldc           #91                 // String Unresolved compilation problem: \n\tMatrix cannot be resolved to a type\n
         6: invokespecial #21                 // Method java/lang/Error."<init>":(Ljava/lang/String;)V
         9: athrow
      LineNumberTable:
        line 1093: 0
      LocalVariableTable:
        Start  Length  Slot  Name   Signature
            0      10     0  this   Lorg/episteme/nativ/mathematics/linearalgebra/backends/NativeMPFRSparseLinearAlgebraBackend;
      LocalVariableTypeTable:
        Start  Length  Slot  Name   Signature
            0      10     0  this   Lorg/episteme/nativ/mathematics/linearalgebra/backends/NativeMPFRSparseLinearAlgebraBackend<TE;>;

  public Matrix<E> multiply(Matrix<E>, Matrix<E>);
    descriptor: (LMatrix;LMatrix;)LMatrix;
    flags: (0x0001) ACC_PUBLIC
    Signature: #165                         // (LMatrix<TE;>;LMatrix<TE;>;)LMatrix<TE;>;
    Code:
      stack=3, locals=3, args_size=3
         0: new           #17                 // class java/lang/Error
         3: dup
         4: ldc           #169                // String Unresolved compilation problems: \n\tMatrix cannot be resolved to a type\n\tComplex cannot be resolved to a type\n\tComplex cannot be resolved to a type\n\tComplex cannot be resolved to a type\n\tComplex cannot be resolved to a type\n\tComplex cannot be resolved\n\tThe method readMPFR(MemorySegment, Arena) from the type NativeMPFRSparseLinearAlgebraBackend<E> refers to the missing type Real\n\tThe method readMPFR(MemorySegment, Arena) from the type NativeMPFRSparseLinearAlgebraBackend<E> refers to the missing type Real\n\tReal cannot be resolved to a type\n\tReal cannot be resolved to a type\n\tReal cannot be resolved to a type\n\tReal cannot be resolved to a type\n\tThe method readMPFR(MemorySegment, Arena) from the type NativeMPFRSparseLinearAlgebraBackend<E> refers to the missing type Real\n
         6: invokespecial #21                 // Method java/lang/Error."<init>":(Ljava/lang/String;)V
         9: athrow
      LineNumberTable:
        line 1184: 0
      LocalVariableTable:
        Start  Length  Slot  Name   Signature
            0      10     0  this   Lorg/episteme/nativ/mathematics/linearalgebra/backends/NativeMPFRSparseLinearAlgebraBackend;
      LocalVariableTypeTable:
        Start  Length  Slot  Name   Signature
            0      10     0  this   Lorg/episteme/nativ/mathematics/linearalgebra/backends/NativeMPFRSparseLinearAlgebraBackend<TE;>;

  public E dot(Vector<E>, Vector<E>);
    descriptor: (LVector;LVector;)Ljava/lang/Object;
    flags: (0x0001) ACC_PUBLIC
    Signature: #173                         // (LVector<TE;>;LVector<TE;>;)TE;
    Code:
      stack=3, locals=3, args_size=3
         0: new           #17                 // class java/lang/Error
         3: dup
         4: ldc           #161                // String Unresolved compilation problem: \n\tVector cannot be resolved to a type\n
         6: invokespecial #21                 // Method java/lang/Error."<init>":(Ljava/lang/String;)V
         9: athrow
      LineNumberTable:
        line 1298: 0
      LocalVariableTable:
        Start  Length  Slot  Name   Signature
            0      10     0  this   Lorg/episteme/nativ/mathematics/linearalgebra/backends/NativeMPFRSparseLinearAlgebraBackend;
      LocalVariableTypeTable:
        Start  Length  Slot  Name   Signature
            0      10     0  this   Lorg/episteme/nativ/mathematics/linearalgebra/backends/NativeMPFRSparseLinearAlgebraBackend<TE;>;

  public E norm(Vector<E>);
    descriptor: (LVector;)Ljava/lang/Object;
    flags: (0x0001) ACC_PUBLIC
    Signature: #176                         // (LVector<TE;>;)TE;
    Code:
      stack=3, locals=2, args_size=2
         0: new           #17                 // class java/lang/Error
         3: dup
         4: ldc           #161                // String Unresolved compilation problem: \n\tVector cannot be resolved to a type\n
         6: invokespecial #21                 // Method java/lang/Error."<init>":(Ljava/lang/String;)V
         9: athrow
      LineNumberTable:
        line 1332: 0
      LocalVariableTable:
        Start  Length  Slot  Name   Signature
            0      10     0  this   Lorg/episteme/nativ/mathematics/linearalgebra/backends/NativeMPFRSparseLinearAlgebraBackend;
      LocalVariableTypeTable:
        Start  Length  Slot  Name   Signature
            0      10     0  this   Lorg/episteme/nativ/mathematics/linearalgebra/backends/NativeMPFRSparseLinearAlgebraBackend<TE;>;

  public Vector<E> solve(Matrix<E>, Vector<E>);
    descriptor: (LMatrix;LVector;)LVector;
    flags: (0x0001) ACC_PUBLIC
    Signature: #137                         // (LMatrix<TE;>;LVector<TE;>;)LVector<TE;>;
    Code:
      stack=3, locals=3, args_size=3
         0: new           #17                 // class java/lang/Error
         3: dup
         4: ldc           #91                 // String Unresolved compilation problem: \n\tMatrix cannot be resolved to a type\n
         6: invokespecial #21                 // Method java/lang/Error."<init>":(Ljava/lang/String;)V
         9: athrow
      LineNumberTable:
        line 1363: 0
      LocalVariableTable:
        Start  Length  Slot  Name   Signature
            0      10     0  this   Lorg/episteme/nativ/mathematics/linearalgebra/backends/NativeMPFRSparseLinearAlgebraBackend;
      LocalVariableTypeTable:
        Start  Length  Slot  Name   Signature
            0      10     0  this   Lorg/episteme/nativ/mathematics/linearalgebra/backends/NativeMPFRSparseLinearAlgebraBackend<TE;>;

  boolean isLowerTriangular(Matrix<E>);
    descriptor: (LMatrix;)Z
    flags: (0x0000)
    Signature: #180                         // (LMatrix<TE;>;)Z
    Code:
      stack=3, locals=2, args_size=2
         0: new           #17                 // class java/lang/Error
         3: dup
         4: ldc           #91                 // String Unresolved compilation problem: \n\tMatrix cannot be resolved to a type\n
         6: invokespecial #21                 // Method java/lang/Error."<init>":(Ljava/lang/String;)V
         9: athrow
      LineNumberTable:
        line 1390: 0
      LocalVariableTable:
        Start  Length  Slot  Name   Signature
            0      10     0  this   Lorg/episteme/nativ/mathematics/linearalgebra/backends/NativeMPFRSparseLinearAlgebraBackend;
      LocalVariableTypeTable:
        Start  Length  Slot  Name   Signature
            0      10     0  this   Lorg/episteme/nativ/mathematics/linearalgebra/backends/NativeMPFRSparseLinearAlgebraBackend<TE;>;

  boolean isUpperTriangular(Matrix<E>);
    descriptor: (LMatrix;)Z
    flags: (0x0000)
    Signature: #180                         // (LMatrix<TE;>;)Z
    Code:
      stack=3, locals=2, args_size=2
         0: new           #17                 // class java/lang/Error
         3: dup
         4: ldc           #91                 // String Unresolved compilation problem: \n\tMatrix cannot be resolved to a type\n
         6: invokespecial #21                 // Method java/lang/Error."<init>":(Ljava/lang/String;)V
         9: athrow
      LineNumberTable:
        line 1410: 0
      LocalVariableTable:
        Start  Length  Slot  Name   Signature
            0      10     0  this   Lorg/episteme/nativ/mathematics/linearalgebra/backends/NativeMPFRSparseLinearAlgebraBackend;
      LocalVariableTypeTable:
        Start  Length  Slot  Name   Signature
            0      10     0  this   Lorg/episteme/nativ/mathematics/linearalgebra/backends/NativeMPFRSparseLinearAlgebraBackend<TE;>;

  public Vector<E> solveTriangular(Matrix<E>, Vector<E>, boolean, boolean, boolean, boolean);
    descriptor: (LMatrix;LVector;ZZZZ)LVector;
    flags: (0x0001) ACC_PUBLIC
    Signature: #184                         // (LMatrix<TE;>;LVector<TE;>;ZZZZ)LVector<TE;>;
    Code:
      stack=3, locals=7, args_size=7
         0: new           #17                 // class java/lang/Error
         3: dup
         4: ldc           #91                 // String Unresolved compilation problem: \n\tMatrix cannot be resolved to a type\n
         6: invokespecial #21                 // Method java/lang/Error."<init>":(Ljava/lang/String;)V
         9: athrow
      LineNumberTable:
        line 1432: 0
      LocalVariableTable:
        Start  Length  Slot  Name   Signature
            0      10     0  this   Lorg/episteme/nativ/mathematics/linearalgebra/backends/NativeMPFRSparseLinearAlgebraBackend;
      LocalVariableTypeTable:
        Start  Length  Slot  Name   Signature
            0      10     0  this   Lorg/episteme/nativ/mathematics/linearalgebra/backends/NativeMPFRSparseLinearAlgebraBackend<TE;>;

  private void complexDiv(java.lang.foreign.MemorySegment, java.lang.foreign.MemorySegment, java.lang.foreign.MemorySegment, java.lang.foreign.MemorySegment, java.lang.foreign.MemorySegment, java.lang.foreign.MemorySegment, long, java.lang.foreign.Arena) throws java.lang.Throwable;
    descriptor: (Ljava/lang/foreign/MemorySegment;Ljava/lang/foreign/MemorySegment;Ljava/lang/foreign/MemorySegment;Ljava/lang/foreign/MemorySegment;Ljava/lang/foreign/MemorySegment;Ljava/lang/foreign/MemorySegment;JLjava/lang/foreign/Arena;)V
    flags: (0x0002) ACC_PRIVATE
    Exceptions:
      throws java.lang.Throwable
    Code:
      stack=3, locals=10, args_size=9
         0: new           #17                 // class java/lang/Error
         3: dup
         4: ldc           #31                 // String Unresolved compilation problem: \n
         6: invokespecial #21                 // Method java/lang/Error."<init>":(Ljava/lang/String;)V
         9: athrow
      LineNumberTable:
        line 1623: 0
      LocalVariableTable:
        Start  Length  Slot  Name   Signature
            0      10     0  this   Lorg/episteme/nativ/mathematics/linearalgebra/backends/NativeMPFRSparseLinearAlgebraBackend;
      LocalVariableTypeTable:
        Start  Length  Slot  Name   Signature
            0      10     0  this   Lorg/episteme/nativ/mathematics/linearalgebra/backends/NativeMPFRSparseLinearAlgebraBackend<TE;>;

  public Matrix<E> transpose(Matrix<E>);
    descriptor: (LMatrix;)LMatrix;
    flags: (0x0001) ACC_PUBLIC
    Signature: #189                         // (LMatrix<TE;>;)LMatrix<TE;>;
    Code:
      stack=3, locals=2, args_size=2
         0: new           #17                 // class java/lang/Error
         3: dup
         4: ldc           #91                 // String Unresolved compilation problem: \n\tMatrix cannot be resolved to a type\n
         6: invokespecial #21                 // Method java/lang/Error."<init>":(Ljava/lang/String;)V
         9: athrow
      LineNumberTable:
        line 1658: 0
      LocalVariableTable:
        Start  Length  Slot  Name   Signature
            0      10     0  this   Lorg/episteme/nativ/mathematics/linearalgebra/backends/NativeMPFRSparseLinearAlgebraBackend;
      LocalVariableTypeTable:
        Start  Length  Slot  Name   Signature
            0      10     0  this   Lorg/episteme/nativ/mathematics/linearalgebra/backends/NativeMPFRSparseLinearAlgebraBackend<TE;>;

  public Matrix<E> exp(Matrix<E>);
    descriptor: (LMatrix;)LMatrix;
    flags: (0x0001) ACC_PUBLIC
    Signature: #189                         // (LMatrix<TE;>;)LMatrix<TE;>;
    Code:
      stack=3, locals=2, args_size=2
         0: new           #17                 // class java/lang/Error
         3: dup
         4: ldc           #91                 // String Unresolved compilation problem: \n\tMatrix cannot be resolved to a type\n
         6: invokespecial #21                 // Method java/lang/Error."<init>":(Ljava/lang/String;)V
         9: athrow
      LineNumberTable:
        line 1680: 0
      LocalVariableTable:
        Start  Length  Slot  Name   Signature
            0      10     0  this   Lorg/episteme/nativ/mathematics/linearalgebra/backends/NativeMPFRSparseLinearAlgebraBackend;
      LocalVariableTypeTable:
        Start  Length  Slot  Name   Signature
            0      10     0  this   Lorg/episteme/nativ/mathematics/linearalgebra/backends/NativeMPFRSparseLinearAlgebraBackend<TE;>;

  public Matrix<E> log(Matrix<E>);
    descriptor: (LMatrix;)LMatrix;
    flags: (0x0001) ACC_PUBLIC
    Signature: #189                         // (LMatrix<TE;>;)LMatrix<TE;>;
    Code:
      stack=3, locals=2, args_size=2
         0: new           #17                 // class java/lang/Error
         3: dup
         4: ldc           #91                 // String Unresolved compilation problem: \n\tMatrix cannot be resolved to a type\n
         6: invokespecial #21                 // Method java/lang/Error."<init>":(Ljava/lang/String;)V
         9: athrow
      LineNumberTable:
        line 1681: 0
      LocalVariableTable:
        Start  Length  Slot  Name   Signature
            0      10     0  this   Lorg/episteme/nativ/mathematics/linearalgebra/backends/NativeMPFRSparseLinearAlgebraBackend;
      LocalVariableTypeTable:
        Start  Length  Slot  Name   Signature
            0      10     0  this   Lorg/episteme/nativ/mathematics/linearalgebra/backends/NativeMPFRSparseLinearAlgebraBackend<TE;>;

  public Matrix<E> log10(Matrix<E>);
    descriptor: (LMatrix;)LMatrix;
    flags: (0x0001) ACC_PUBLIC
    Signature: #189                         // (LMatrix<TE;>;)LMatrix<TE;>;
    Code:
      stack=3, locals=2, args_size=2
         0: new           #17                 // class java/lang/Error
         3: dup
         4: ldc           #91                 // String Unresolved compilation problem: \n\tMatrix cannot be resolved to a type\n
         6: invokespecial #21                 // Method java/lang/Error."<init>":(Ljava/lang/String;)V
         9: athrow
      LineNumberTable:
        line 1682: 0
      LocalVariableTable:
        Start  Length  Slot  Name   Signature
            0      10     0  this   Lorg/episteme/nativ/mathematics/linearalgebra/backends/NativeMPFRSparseLinearAlgebraBackend;
      LocalVariableTypeTable:
        Start  Length  Slot  Name   Signature
            0      10     0  this   Lorg/episteme/nativ/mathematics/linearalgebra/backends/NativeMPFRSparseLinearAlgebraBackend<TE;>;

  public Matrix<E> sin(Matrix<E>);
    descriptor: (LMatrix;)LMatrix;
    flags: (0x0001) ACC_PUBLIC
    Signature: #189                         // (LMatrix<TE;>;)LMatrix<TE;>;
    Code:
      stack=3, locals=2, args_size=2
         0: new           #17                 // class java/lang/Error
         3: dup
         4: ldc           #91                 // String Unresolved compilation problem: \n\tMatrix cannot be resolved to a type\n
         6: invokespecial #21                 // Method java/lang/Error."<init>":(Ljava/lang/String;)V
         9: athrow
      LineNumberTable:
        line 1683: 0
      LocalVariableTable:
        Start  Length  Slot  Name   Signature
            0      10     0  this   Lorg/episteme/nativ/mathematics/linearalgebra/backends/NativeMPFRSparseLinearAlgebraBackend;
      LocalVariableTypeTable:
        Start  Length  Slot  Name   Signature
            0      10     0  this   Lorg/episteme/nativ/mathematics/linearalgebra/backends/NativeMPFRSparseLinearAlgebraBackend<TE;>;

  public Matrix<E> cos(Matrix<E>);
    descriptor: (LMatrix;)LMatrix;
    flags: (0x0001) ACC_PUBLIC
    Signature: #189                         // (LMatrix<TE;>;)LMatrix<TE;>;
    Code:
      stack=3, locals=2, args_size=2
         0: new           #17                 // class java/lang/Error
         3: dup
         4: ldc           #91                 // String Unresolved compilation problem: \n\tMatrix cannot be resolved to a type\n
         6: invokespecial #21                 // Method java/lang/Error."<init>":(Ljava/lang/String;)V
         9: athrow
      LineNumberTable:
        line 1684: 0
      LocalVariableTable:
        Start  Length  Slot  Name   Signature
            0      10     0  this   Lorg/episteme/nativ/mathematics/linearalgebra/backends/NativeMPFRSparseLinearAlgebraBackend;
      LocalVariableTypeTable:
        Start  Length  Slot  Name   Signature
            0      10     0  this   Lorg/episteme/nativ/mathematics/linearalgebra/backends/NativeMPFRSparseLinearAlgebraBackend<TE;>;

  public Matrix<E> tan(Matrix<E>);
    descriptor: (LMatrix;)LMatrix;
    flags: (0x0001) ACC_PUBLIC
    Signature: #189                         // (LMatrix<TE;>;)LMatrix<TE;>;
    Code:
      stack=3, locals=2, args_size=2
         0: new           #17                 // class java/lang/Error
         3: dup
         4: ldc           #91                 // String Unresolved compilation problem: \n\tMatrix cannot be resolved to a type\n
         6: invokespecial #21                 // Method java/lang/Error."<init>":(Ljava/lang/String;)V
         9: athrow
      LineNumberTable:
        line 1685: 0
      LocalVariableTable:
        Start  Length  Slot  Name   Signature
            0      10     0  this   Lorg/episteme/nativ/mathematics/linearalgebra/backends/NativeMPFRSparseLinearAlgebraBackend;
      LocalVariableTypeTable:
        Start  Length  Slot  Name   Signature
            0      10     0  this   Lorg/episteme/nativ/mathematics/linearalgebra/backends/NativeMPFRSparseLinearAlgebraBackend<TE;>;

  public Matrix<E> asin(Matrix<E>);
    descriptor: (LMatrix;)LMatrix;
    flags: (0x0001) ACC_PUBLIC
    Signature: #189                         // (LMatrix<TE;>;)LMatrix<TE;>;
    Code:
      stack=3, locals=2, args_size=2
         0: new           #17                 // class java/lang/Error
         3: dup
         4: ldc           #91                 // String Unresolved compilation problem: \n\tMatrix cannot be resolved to a type\n
         6: invokespecial #21                 // Method java/lang/Error."<init>":(Ljava/lang/String;)V
         9: athrow
      LineNumberTable:
        line 1686: 0
      LocalVariableTable:
        Start  Length  Slot  Name   Signature
            0      10     0  this   Lorg/episteme/nativ/mathematics/linearalgebra/backends/NativeMPFRSparseLinearAlgebraBackend;
      LocalVariableTypeTable:
        Start  Length  Slot  Name   Signature
            0      10     0  this   Lorg/episteme/nativ/mathematics/linearalgebra/backends/NativeMPFRSparseLinearAlgebraBackend<TE;>;

  public Matrix<E> acos(Matrix<E>);
    descriptor: (LMatrix;)LMatrix;
    flags: (0x0001) ACC_PUBLIC
    Signature: #189                         // (LMatrix<TE;>;)LMatrix<TE;>;
    Code:
      stack=3, locals=2, args_size=2
         0: new           #17                 // class java/lang/Error
         3: dup
         4: ldc           #91                 // String Unresolved compilation problem: \n\tMatrix cannot be resolved to a type\n
         6: invokespecial #21                 // Method java/lang/Error."<init>":(Ljava/lang/String;)V
         9: athrow
      LineNumberTable:
        line 1687: 0
      LocalVariableTable:
        Start  Length  Slot  Name   Signature
            0      10     0  this   Lorg/episteme/nativ/mathematics/linearalgebra/backends/NativeMPFRSparseLinearAlgebraBackend;
      LocalVariableTypeTable:
        Start  Length  Slot  Name   Signature
            0      10     0  this   Lorg/episteme/nativ/mathematics/linearalgebra/backends/NativeMPFRSparseLinearAlgebraBackend<TE;>;

  public Matrix<E> atan(Matrix<E>);
    descriptor: (LMatrix;)LMatrix;
    flags: (0x0001) ACC_PUBLIC
    Signature: #189                         // (LMatrix<TE;>;)LMatrix<TE;>;
    Code:
      stack=3, locals=2, args_size=2
         0: new           #17                 // class java/lang/Error
         3: dup
         4: ldc           #91                 // String Unresolved compilation problem: \n\tMatrix cannot be resolved to a type\n
         6: invokespecial #21                 // Method java/lang/Error."<init>":(Ljava/lang/String;)V
         9: athrow
      LineNumberTable:
        line 1688: 0
      LocalVariableTable:
        Start  Length  Slot  Name   Signature
            0      10     0  this   Lorg/episteme/nativ/mathematics/linearalgebra/backends/NativeMPFRSparseLinearAlgebraBackend;
      LocalVariableTypeTable:
        Start  Length  Slot  Name   Signature
            0      10     0  this   Lorg/episteme/nativ/mathematics/linearalgebra/backends/NativeMPFRSparseLinearAlgebraBackend<TE;>;

  public Matrix<E> sinh(Matrix<E>);
    descriptor: (LMatrix;)LMatrix;
    flags: (0x0001) ACC_PUBLIC
    Signature: #189                         // (LMatrix<TE;>;)LMatrix<TE;>;
    Code:
      stack=3, locals=2, args_size=2
         0: new           #17                 // class java/lang/Error
         3: dup
         4: ldc           #91                 // String Unresolved compilation problem: \n\tMatrix cannot be resolved to a type\n
         6: invokespecial #21                 // Method java/lang/Error."<init>":(Ljava/lang/String;)V
         9: athrow
      LineNumberTable:
        line 1689: 0
      LocalVariableTable:
        Start  Length  Slot  Name   Signature
            0      10     0  this   Lorg/episteme/nativ/mathematics/linearalgebra/backends/NativeMPFRSparseLinearAlgebraBackend;
      LocalVariableTypeTable:
        Start  Length  Slot  Name   Signature
            0      10     0  this   Lorg/episteme/nativ/mathematics/linearalgebra/backends/NativeMPFRSparseLinearAlgebraBackend<TE;>;

  public Matrix<E> cosh(Matrix<E>);
    descriptor: (LMatrix;)LMatrix;
    flags: (0x0001) ACC_PUBLIC
    Signature: #189                         // (LMatrix<TE;>;)LMatrix<TE;>;
    Code:
      stack=3, locals=2, args_size=2
         0: new           #17                 // class java/lang/Error
         3: dup
         4: ldc           #91                 // String Unresolved compilation problem: \n\tMatrix cannot be resolved to a type\n
         6: invokespecial #21                 // Method java/lang/Error."<init>":(Ljava/lang/String;)V
         9: athrow
      LineNumberTable:
        line 1690: 0
      LocalVariableTable:
        Start  Length  Slot  Name   Signature
            0      10     0  this   Lorg/episteme/nativ/mathematics/linearalgebra/backends/NativeMPFRSparseLinearAlgebraBackend;
      LocalVariableTypeTable:
        Start  Length  Slot  Name   Signature
            0      10     0  this   Lorg/episteme/nativ/mathematics/linearalgebra/backends/NativeMPFRSparseLinearAlgebraBackend<TE;>;

  public Matrix<E> tanh(Matrix<E>);
    descriptor: (LMatrix;)LMatrix;
    flags: (0x0001) ACC_PUBLIC
    Signature: #189                         // (LMatrix<TE;>;)LMatrix<TE;>;
    Code:
      stack=3, locals=2, args_size=2
         0: new           #17                 // class java/lang/Error
         3: dup
         4: ldc           #91                 // String Unresolved compilation problem: \n\tMatrix cannot be resolved to a type\n
         6: invokespecial #21                 // Method java/lang/Error."<init>":(Ljava/lang/String;)V
         9: athrow
      LineNumberTable:
        line 1691: 0
      LocalVariableTable:
        Start  Length  Slot  Name   Signature
            0      10     0  this   Lorg/episteme/nativ/mathematics/linearalgebra/backends/NativeMPFRSparseLinearAlgebraBackend;
      LocalVariableTypeTable:
        Start  Length  Slot  Name   Signature
            0      10     0  this   Lorg/episteme/nativ/mathematics/linearalgebra/backends/NativeMPFRSparseLinearAlgebraBackend<TE;>;

  public Matrix<E> asinh(Matrix<E>);
    descriptor: (LMatrix;)LMatrix;
    flags: (0x0001) ACC_PUBLIC
    Signature: #189                         // (LMatrix<TE;>;)LMatrix<TE;>;
    Code:
      stack=3, locals=2, args_size=2
         0: new           #17                 // class java/lang/Error
         3: dup
         4: ldc           #91                 // String Unresolved compilation problem: \n\tMatrix cannot be resolved to a type\n
         6: invokespecial #21                 // Method java/lang/Error."<init>":(Ljava/lang/String;)V
         9: athrow
      LineNumberTable:
        line 1692: 0
      LocalVariableTable:
        Start  Length  Slot  Name   Signature
            0      10     0  this   Lorg/episteme/nativ/mathematics/linearalgebra/backends/NativeMPFRSparseLinearAlgebraBackend;
      LocalVariableTypeTable:
        Start  Length  Slot  Name   Signature
            0      10     0  this   Lorg/episteme/nativ/mathematics/linearalgebra/backends/NativeMPFRSparseLinearAlgebraBackend<TE;>;

  public Matrix<E> acosh(Matrix<E>);
    descriptor: (LMatrix;)LMatrix;
    flags: (0x0001) ACC_PUBLIC
    Signature: #189                         // (LMatrix<TE;>;)LMatrix<TE;>;
    Code:
      stack=3, locals=2, args_size=2
         0: new           #17                 // class java/lang/Error
         3: dup
         4: ldc           #91                 // String Unresolved compilation problem: \n\tMatrix cannot be resolved to a type\n
         6: invokespecial #21                 // Method java/lang/Error."<init>":(Ljava/lang/String;)V
         9: athrow
      LineNumberTable:
        line 1693: 0
      LocalVariableTable:
        Start  Length  Slot  Name   Signature
            0      10     0  this   Lorg/episteme/nativ/mathematics/linearalgebra/backends/NativeMPFRSparseLinearAlgebraBackend;
      LocalVariableTypeTable:
        Start  Length  Slot  Name   Signature
            0      10     0  this   Lorg/episteme/nativ/mathematics/linearalgebra/backends/NativeMPFRSparseLinearAlgebraBackend<TE;>;

  public Matrix<E> atanh(Matrix<E>);
    descriptor: (LMatrix;)LMatrix;
    flags: (0x0001) ACC_PUBLIC
    Signature: #189                         // (LMatrix<TE;>;)LMatrix<TE;>;
    Code:
      stack=3, locals=2, args_size=2
         0: new           #17                 // class java/lang/Error
         3: dup
         4: ldc           #91                 // String Unresolved compilation problem: \n\tMatrix cannot be resolved to a type\n
         6: invokespecial #21                 // Method java/lang/Error."<init>":(Ljava/lang/String;)V
         9: athrow
      LineNumberTable:
        line 1694: 0
      LocalVariableTable:
        Start  Length  Slot  Name   Signature
            0      10     0  this   Lorg/episteme/nativ/mathematics/linearalgebra/backends/NativeMPFRSparseLinearAlgebraBackend;
      LocalVariableTypeTable:
        Start  Length  Slot  Name   Signature
            0      10     0  this   Lorg/episteme/nativ/mathematics/linearalgebra/backends/NativeMPFRSparseLinearAlgebraBackend<TE;>;

  public Matrix<E> sqrt(Matrix<E>);
    descriptor: (LMatrix;)LMatrix;
    flags: (0x0001) ACC_PUBLIC
    Signature: #189                         // (LMatrix<TE;>;)LMatrix<TE;>;
    Code:
      stack=3, locals=2, args_size=2
         0: new           #17                 // class java/lang/Error
         3: dup
         4: ldc           #91                 // String Unresolved compilation problem: \n\tMatrix cannot be resolved to a type\n
         6: invokespecial #21                 // Method java/lang/Error."<init>":(Ljava/lang/String;)V
         9: athrow
      LineNumberTable:
        line 1695: 0
      LocalVariableTable:
        Start  Length  Slot  Name   Signature
            0      10     0  this   Lorg/episteme/nativ/mathematics/linearalgebra/backends/NativeMPFRSparseLinearAlgebraBackend;
      LocalVariableTypeTable:
        Start  Length  Slot  Name   Signature
            0      10     0  this   Lorg/episteme/nativ/mathematics/linearalgebra/backends/NativeMPFRSparseLinearAlgebraBackend<TE;>;

  public Matrix<E> cbrt(Matrix<E>);
    descriptor: (LMatrix;)LMatrix;
    flags: (0x0001) ACC_PUBLIC
    Signature: #189                         // (LMatrix<TE;>;)LMatrix<TE;>;
    Code:
      stack=3, locals=2, args_size=2
         0: new           #17                 // class java/lang/Error
         3: dup
         4: ldc           #91                 // String Unresolved compilation problem: \n\tMatrix cannot be resolved to a type\n
         6: invokespecial #21                 // Method java/lang/Error."<init>":(Ljava/lang/String;)V
         9: athrow
      LineNumberTable:
        line 1696: 0
      LocalVariableTable:
        Start  Length  Slot  Name   Signature
            0      10     0  this   Lorg/episteme/nativ/mathematics/linearalgebra/backends/NativeMPFRSparseLinearAlgebraBackend;
      LocalVariableTypeTable:
        Start  Length  Slot  Name   Signature
            0      10     0  this   Lorg/episteme/nativ/mathematics/linearalgebra/backends/NativeMPFRSparseLinearAlgebraBackend<TE;>;

  boolean isComplex(Matrix<E>);
    descriptor: (LMatrix;)Z
    flags: (0x0000)
    Signature: #180                         // (LMatrix<TE;>;)Z
    Code:
      stack=3, locals=2, args_size=2
         0: new           #17                 // class java/lang/Error
         3: dup
         4: ldc           #31                 // String Unresolved compilation problem: \n
         6: invokespecial #21                 // Method java/lang/Error."<init>":(Ljava/lang/String;)V
         9: athrow
      LineNumberTable:
        line 1698: 0
      LocalVariableTable:
        Start  Length  Slot  Name   Signature
            0      10     0  this   Lorg/episteme/nativ/mathematics/linearalgebra/backends/NativeMPFRSparseLinearAlgebraBackend;
      LocalVariableTypeTable:
        Start  Length  Slot  Name   Signature
            0      10     0  this   Lorg/episteme/nativ/mathematics/linearalgebra/backends/NativeMPFRSparseLinearAlgebraBackend<TE;>;

  boolean isComplex(Ring<?>);
    descriptor: (LRing;)Z
    flags: (0x0000)
    Signature: #112                         // (LRing<*>;)Z
    Code:
      stack=3, locals=2, args_size=2
         0: new           #17                 // class java/lang/Error
         3: dup
         4: ldc           #31                 // String Unresolved compilation problem: \n
         6: invokespecial #21                 // Method java/lang/Error."<init>":(Ljava/lang/String;)V
         9: athrow
      LineNumberTable:
        line 1702: 0
      LocalVariableTable:
        Start  Length  Slot  Name   Signature
            0      10     0  this   Lorg/episteme/nativ/mathematics/linearalgebra/backends/NativeMPFRSparseLinearAlgebraBackend;
      LocalVariableTypeTable:
        Start  Length  Slot  Name   Signature
            0      10     0  this   Lorg/episteme/nativ/mathematics/linearalgebra/backends/NativeMPFRSparseLinearAlgebraBackend<TE;>;

  public Matrix<E> applyTranscendental(Matrix<E>, java.lang.String, java.lang.Object...);
    descriptor: (LMatrix;Ljava/lang/String;[Ljava/lang/Object;)LMatrix;
    flags: (0x0081) ACC_PUBLIC, ACC_VARARGS
    Signature: #209                         // (LMatrix<TE;>;Ljava/lang/String;[Ljava/lang/Object;)LMatrix<TE;>;
    Code:
      stack=3, locals=4, args_size=4
         0: new           #17                 // class java/lang/Error
         3: dup
         4: ldc           #31                 // String Unresolved compilation problem: \n
         6: invokespecial #21                 // Method java/lang/Error."<init>":(Ljava/lang/String;)V
         9: athrow
      LineNumberTable:
        line 1706: 0
      LocalVariableTable:
        Start  Length  Slot  Name   Signature
            0      10     0  this   Lorg/episteme/nativ/mathematics/linearalgebra/backends/NativeMPFRSparseLinearAlgebraBackend;
      LocalVariableTypeTable:
        Start  Length  Slot  Name   Signature
            0      10     0  this   Lorg/episteme/nativ/mathematics/linearalgebra/backends/NativeMPFRSparseLinearAlgebraBackend<TE;>;

  public Vector<E> conjugateGradient(Matrix<E>, Vector<E>, Vector<E>, E, int);
    descriptor: (LMatrix;LVector;LVector;Ljava/lang/Object;I)LVector;
    flags: (0x0001) ACC_PUBLIC
    Signature: #212                         // (LMatrix<TE;>;LVector<TE;>;LVector<TE;>;TE;I)LVector<TE;>;
    Code:
      stack=3, locals=6, args_size=6
         0: new           #17                 // class java/lang/Error
         3: dup
         4: ldc           #31                 // String Unresolved compilation problem: \n
         6: invokespecial #21                 // Method java/lang/Error."<init>":(Ljava/lang/String;)V
         9: athrow
      LineNumberTable:
        line 1737: 0
      LocalVariableTable:
        Start  Length  Slot  Name   Signature
            0      10     0  this   Lorg/episteme/nativ/mathematics/linearalgebra/backends/NativeMPFRSparseLinearAlgebraBackend;
      LocalVariableTypeTable:
        Start  Length  Slot  Name   Signature
            0      10     0  this   Lorg/episteme/nativ/mathematics/linearalgebra/backends/NativeMPFRSparseLinearAlgebraBackend<TE;>;

  public Vector<E> bicgstab(Matrix<E>, Vector<E>, Vector<E>, E, int);
    descriptor: (LMatrix;LVector;LVector;Ljava/lang/Object;I)LVector;
    flags: (0x0001) ACC_PUBLIC
    Signature: #212                         // (LMatrix<TE;>;LVector<TE;>;LVector<TE;>;TE;I)LVector<TE;>;
    Code:
      stack=3, locals=6, args_size=6
         0: new           #17                 // class java/lang/Error
         3: dup
         4: ldc           #31                 // String Unresolved compilation problem: \n
         6: invokespecial #21                 // Method java/lang/Error."<init>":(Ljava/lang/String;)V
         9: athrow
      LineNumberTable:
        line 1801: 0
      LocalVariableTable:
        Start  Length  Slot  Name   Signature
            0      10     0  this   Lorg/episteme/nativ/mathematics/linearalgebra/backends/NativeMPFRSparseLinearAlgebraBackend;
      LocalVariableTypeTable:
        Start  Length  Slot  Name   Signature
            0      10     0  this   Lorg/episteme/nativ/mathematics/linearalgebra/backends/NativeMPFRSparseLinearAlgebraBackend<TE;>;

  public Vector<E> gmres(Matrix<E>, Vector<E>, Vector<E>, E, int, int);
    descriptor: (LMatrix;LVector;LVector;Ljava/lang/Object;II)LVector;
    flags: (0x0001) ACC_PUBLIC
    Signature: #216                         // (LMatrix<TE;>;LVector<TE;>;LVector<TE;>;TE;II)LVector<TE;>;
    Code:
      stack=3, locals=7, args_size=7
         0: new           #17                 // class java/lang/Error
         3: dup
         4: ldc           #31                 // String Unresolved compilation problem: \n
         6: invokespecial #21                 // Method java/lang/Error."<init>":(Ljava/lang/String;)V
         9: athrow
      LineNumberTable:
        line 1924: 0
      LocalVariableTable:
        Start  Length  Slot  Name   Signature
            0      10     0  this   Lorg/episteme/nativ/mathematics/linearalgebra/backends/NativeMPFRSparseLinearAlgebraBackend;
      LocalVariableTypeTable:
        Start  Length  Slot  Name   Signature
            0      10     0  this   Lorg/episteme/nativ/mathematics/linearalgebra/backends/NativeMPFRSparseLinearAlgebraBackend<TE;>;

  void solveSmallAndCheck(java.lang.Object[][], E, java.lang.foreign.MemorySegment, java.lang.foreign.MemorySegment, int, int, boolean, Ring<E>, long, java.lang.foreign.Arena, org.episteme.nativ.technical.backend.nativ.ResourceTracker) throws java.lang.Throwable;
    descriptor: ([[Ljava/lang/Object;Ljava/lang/Object;Ljava/lang/foreign/MemorySegment;Ljava/lang/foreign/MemorySegment;IIZLRing;JLjava/lang/foreign/Arena;Lorg/episteme/nativ/technical/backend/nativ/ResourceTracker;)V
    flags: (0x0000)
    Exceptions:
      throws java.lang.Throwable
    Signature: #219                         // ([[Ljava/lang/Object;TE;Ljava/lang/foreign/MemorySegment;Ljava/lang/foreign/MemorySegment;IIZLRing<TE;>;JLjava/lang/foreign/Arena;Lorg/episteme/nativ/technical/backend/nativ/ResourceTracker;)V
    Code:
      stack=3, locals=13, args_size=12
         0: new           #17                 // class java/lang/Error
         3: dup
         4: ldc           #31                 // String Unresolved compilation problem: \n
         6: invokespecial #21                 // Method java/lang/Error."<init>":(Ljava/lang/String;)V
         9: athrow
      LineNumberTable:
        line 2024: 0
      LocalVariableTable:
        Start  Length  Slot  Name   Signature
            0      10     0  this   Lorg/episteme/nativ/mathematics/linearalgebra/backends/NativeMPFRSparseLinearAlgebraBackend;
      LocalVariableTypeTable:
        Start  Length  Slot  Name   Signature
            0      10     0  this   Lorg/episteme/nativ/mathematics/linearalgebra/backends/NativeMPFRSparseLinearAlgebraBackend<TE;>;

  private int compare(E, E);
    descriptor: (Ljava/lang/Object;Ljava/lang/Object;)I
    flags: (0x0002) ACC_PRIVATE
    Signature: #222                         // (TE;TE;)I
    Code:
      stack=3, locals=3, args_size=3
         0: new           #17                 // class java/lang/Error
         3: dup
         4: ldc           #31                 // String Unresolved compilation problem: \n
         6: invokespecial #21                 // Method java/lang/Error."<init>":(Ljava/lang/String;)V
         9: athrow
      LineNumberTable:
        line 2406: 0
      LocalVariableTable:
        Start  Length  Slot  Name   Signature
            0      10     0  this   Lorg/episteme/nativ/mathematics/linearalgebra/backends/NativeMPFRSparseLinearAlgebraBackend;
      LocalVariableTypeTable:
        Start  Length  Slot  Name   Signature
            0      10     0  this   Lorg/episteme/nativ/mathematics/linearalgebra/backends/NativeMPFRSparseLinearAlgebraBackend<TE;>;

  private E negate(boolean, E);
    descriptor: (ZLjava/lang/Object;)Ljava/lang/Object;
    flags: (0x0002) ACC_PRIVATE
    Signature: #225                         // (ZTE;)TE;
    Code:
      stack=3, locals=3, args_size=3
         0: new           #17                 // class java/lang/Error
         3: dup
         4: ldc           #31                 // String Unresolved compilation problem: \n
         6: invokespecial #21                 // Method java/lang/Error."<init>":(Ljava/lang/String;)V
         9: athrow
      LineNumberTable:
        line 2430: 0
      LocalVariableTable:
        Start  Length  Slot  Name   Signature
            0      10     0  this   Lorg/episteme/nativ/mathematics/linearalgebra/backends/NativeMPFRSparseLinearAlgebraBackend;
      LocalVariableTypeTable:
        Start  Length  Slot  Name   Signature
            0      10     0  this   Lorg/episteme/nativ/mathematics/linearalgebra/backends/NativeMPFRSparseLinearAlgebraBackend<TE;>;

  private E divide(boolean, E, E);
    descriptor: (ZLjava/lang/Object;Ljava/lang/Object;)Ljava/lang/Object;
    flags: (0x0002) ACC_PRIVATE
    Signature: #228                         // (ZTE;TE;)TE;
    Code:
      stack=3, locals=4, args_size=4
         0: new           #17                 // class java/lang/Error
         3: dup
         4: ldc           #31                 // String Unresolved compilation problem: \n
         6: invokespecial #21                 // Method java/lang/Error."<init>":(Ljava/lang/String;)V
         9: athrow
      LineNumberTable:
        line 2439: 0
      LocalVariableTable:
        Start  Length  Slot  Name   Signature
            0      10     0  this   Lorg/episteme/nativ/mathematics/linearalgebra/backends/NativeMPFRSparseLinearAlgebraBackend;
      LocalVariableTypeTable:
        Start  Length  Slot  Name   Signature
            0      10     0  this   Lorg/episteme/nativ/mathematics/linearalgebra/backends/NativeMPFRSparseLinearAlgebraBackend<TE;>;

  private E multiply(boolean, E, E);
    descriptor: (ZLjava/lang/Object;Ljava/lang/Object;)Ljava/lang/Object;
    flags: (0x0002) ACC_PRIVATE
    Signature: #228                         // (ZTE;TE;)TE;
    Code:
      stack=3, locals=4, args_size=4
         0: new           #17                 // class java/lang/Error
         3: dup
         4: ldc           #31                 // String Unresolved compilation problem: \n
         6: invokespecial #21                 // Method java/lang/Error."<init>":(Ljava/lang/String;)V
         9: athrow
      LineNumberTable:
        line 2449: 0
      LocalVariableTable:
        Start  Length  Slot  Name   Signature
            0      10     0  this   Lorg/episteme/nativ/mathematics/linearalgebra/backends/NativeMPFRSparseLinearAlgebraBackend;
      LocalVariableTypeTable:
        Start  Length  Slot  Name   Signature
            0      10     0  this   Lorg/episteme/nativ/mathematics/linearalgebra/backends/NativeMPFRSparseLinearAlgebraBackend<TE;>;

  Vector<E> backToVector(java.lang.foreign.MemorySegment, int, boolean, Ring<E>, java.lang.foreign.Arena) throws java.lang.Throwable;
    descriptor: (Ljava/lang/foreign/MemorySegment;IZLRing;Ljava/lang/foreign/Arena;)LVector;
    flags: (0x0000)
    Exceptions:
      throws java.lang.Throwable
    Signature: #231                         // (Ljava/lang/foreign/MemorySegment;IZLRing<TE;>;Ljava/lang/foreign/Arena;)LVector<TE;>;
    Code:
      stack=3, locals=6, args_size=6
         0: new           #17                 // class java/lang/Error
         3: dup
         4: ldc           #31                 // String Unresolved compilation problem: \n
         6: invokespecial #21                 // Method java/lang/Error."<init>":(Ljava/lang/String;)V
         9: athrow
      LineNumberTable:
        line 2459: 0
      LocalVariableTable:
        Start  Length  Slot  Name   Signature
            0      10     0  this   Lorg/episteme/nativ/mathematics/linearalgebra/backends/NativeMPFRSparseLinearAlgebraBackend;
      LocalVariableTypeTable:
        Start  Length  Slot  Name   Signature
            0      10     0  this   Lorg/episteme/nativ/mathematics/linearalgebra/backends/NativeMPFRSparseLinearAlgebraBackend<TE;>;

  org.episteme.core.mathematics.numbers.complex.Complex complexTranscendental(org.episteme.core.mathematics.numbers.complex.Complex, java.lang.String, long, java.lang.foreign.Arena, java.lang.Object...);
    descriptor: (Lorg/episteme/core/mathematics/numbers/complex/Complex;Ljava/lang/String;JLjava/lang/foreign/Arena;[Ljava/lang/Object;)Lorg/episteme/core/mathematics/numbers/complex/Complex;
    flags: (0x0080) ACC_VARARGS
    Code:
      stack=3, locals=7, args_size=6
         0: new           #17                 // class java/lang/Error
         3: dup
         4: ldc           #31                 // String Unresolved compilation problem: \n
         6: invokespecial #21                 // Method java/lang/Error."<init>":(Ljava/lang/String;)V
         9: athrow
      LineNumberTable:
        line 2476: 0
      LocalVariableTable:
        Start  Length  Slot  Name   Signature
            0      10     0  this   Lorg/episteme/nativ/mathematics/linearalgebra/backends/NativeMPFRSparseLinearAlgebraBackend;
      LocalVariableTypeTable:
        Start  Length  Slot  Name   Signature
            0      10     0  this   Lorg/episteme/nativ/mathematics/linearalgebra/backends/NativeMPFRSparseLinearAlgebraBackend<TE;>;

  Real realTranscendental(Real, java.lang.String, long, java.lang.foreign.Arena, java.lang.Object...);
    descriptor: (LReal;Ljava/lang/String;JLjava/lang/foreign/Arena;[Ljava/lang/Object;)LReal;
    flags: (0x0080) ACC_VARARGS
    Code:
      stack=3, locals=7, args_size=6
         0: new           #17                 // class java/lang/Error
         3: dup
         4: ldc           #31                 // String Unresolved compilation problem: \n
         6: invokespecial #21                 // Method java/lang/Error."<init>":(Ljava/lang/String;)V
         9: athrow
      LineNumberTable:
        line 2528: 0
      LocalVariableTable:
        Start  Length  Slot  Name   Signature
            0      10     0  this   Lorg/episteme/nativ/mathematics/linearalgebra/backends/NativeMPFRSparseLinearAlgebraBackend;
      LocalVariableTypeTable:
        Start  Length  Slot  Name   Signature
            0      10     0  this   Lorg/episteme/nativ/mathematics/linearalgebra/backends/NativeMPFRSparseLinearAlgebraBackend<TE;>;

  public E determinant(Matrix<E>);
    descriptor: (LMatrix;)Ljava/lang/Object;
    flags: (0x0001) ACC_PUBLIC
    Signature: #90                          // (LMatrix<TE;>;)TE;
    Code:
      stack=3, locals=2, args_size=2
         0: new           #17                 // class java/lang/Error
         3: dup
         4: ldc           #31                 // String Unresolved compilation problem: \n
         6: invokespecial #21                 // Method java/lang/Error."<init>":(Ljava/lang/String;)V
         9: athrow
      LineNumberTable:
        line 2571: 0
      LocalVariableTable:
        Start  Length  Slot  Name   Signature
            0      10     0  this   Lorg/episteme/nativ/mathematics/linearalgebra/backends/NativeMPFRSparseLinearAlgebraBackend;
      LocalVariableTypeTable:
        Start  Length  Slot  Name   Signature
            0      10     0  this   Lorg/episteme/nativ/mathematics/linearalgebra/backends/NativeMPFRSparseLinearAlgebraBackend<TE;>;

  public Matrix<E> inverse(Matrix<E>);
    descriptor: (LMatrix;)LMatrix;
    flags: (0x0001) ACC_PUBLIC
    Signature: #189                         // (LMatrix<TE;>;)LMatrix<TE;>;
    Code:
      stack=3, locals=2, args_size=2
         0: new           #17                 // class java/lang/Error
         3: dup
         4: ldc           #31                 // String Unresolved compilation problem: \n
         6: invokespecial #21                 // Method java/lang/Error."<init>":(Ljava/lang/String;)V
         9: athrow
      LineNumberTable:
        line 2576: 0
      LocalVariableTable:
        Start  Length  Slot  Name   Signature
            0      10     0  this   Lorg/episteme/nativ/mathematics/linearalgebra/backends/NativeMPFRSparseLinearAlgebraBackend;
      LocalVariableTypeTable:
        Start  Length  Slot  Name   Signature
            0      10     0  this   Lorg/episteme/nativ/mathematics/linearalgebra/backends/NativeMPFRSparseLinearAlgebraBackend<TE;>;

  private static void clearMPFRArray(java.lang.foreign.MemorySegment, int);
    descriptor: (Ljava/lang/foreign/MemorySegment;I)V
    flags: (0x000a) ACC_PRIVATE, ACC_STATIC
    Code:
      stack=3, locals=2, args_size=2
         0: new           #17                 // class java/lang/Error
         3: dup
         4: ldc           #31                 // String Unresolved compilation problem: \n
         6: invokespecial #21                 // Method java/lang/Error."<init>":(Ljava/lang/String;)V
         9: athrow
      LineNumberTable:
        line 2593: 0
      LocalVariableTable:
        Start  Length  Slot  Name   Signature

  public Vector<E> normalize(Vector<E>);
    descriptor: (LVector;)LVector;
    flags: (0x0001) ACC_PUBLIC
    Signature: #242                         // (LVector<TE;>;)LVector<TE;>;
    Code:
      stack=3, locals=2, args_size=2
         0: new           #17                 // class java/lang/Error
         3: dup
         4: ldc           #31                 // String Unresolved compilation problem: \n
         6: invokespecial #21                 // Method java/lang/Error."<init>":(Ljava/lang/String;)V
         9: athrow
      LineNumberTable:
        line 2609: 0
      LocalVariableTable:
        Start  Length  Slot  Name   Signature
            0      10     0  this   Lorg/episteme/nativ/mathematics/linearalgebra/backends/NativeMPFRSparseLinearAlgebraBackend;
      LocalVariableTypeTable:
        Start  Length  Slot  Name   Signature
            0      10     0  this   Lorg/episteme/nativ/mathematics/linearalgebra/backends/NativeMPFRSparseLinearAlgebraBackend<TE;>;

  public Vector<E> cross(Vector<E>, Vector<E>);
    descriptor: (LVector;LVector;)LVector;
    flags: (0x0001) ACC_PUBLIC
    Signature: #167                         // (LVector<TE;>;LVector<TE;>;)LVector<TE;>;
    Code:
      stack=3, locals=3, args_size=3
         0: new           #17                 // class java/lang/Error
         3: dup
         4: ldc           #31                 // String Unresolved compilation problem: \n
         6: invokespecial #21                 // Method java/lang/Error."<init>":(Ljava/lang/String;)V
         9: athrow
      LineNumberTable:
        line 2628: 0
      LocalVariableTable:
        Start  Length  Slot  Name   Signature
            0      10     0  this   Lorg/episteme/nativ/mathematics/linearalgebra/backends/NativeMPFRSparseLinearAlgebraBackend;
      LocalVariableTypeTable:
        Start  Length  Slot  Name   Signature
            0      10     0  this   Lorg/episteme/nativ/mathematics/linearalgebra/backends/NativeMPFRSparseLinearAlgebraBackend<TE;>;

  public E angle(Vector<E>, Vector<E>);
    descriptor: (LVector;LVector;)Ljava/lang/Object;
    flags: (0x0001) ACC_PUBLIC
    Signature: #173                         // (LVector<TE;>;LVector<TE;>;)TE;
    Code:
      stack=3, locals=3, args_size=3
         0: new           #17                 // class java/lang/Error
         3: dup
         4: ldc           #31                 // String Unresolved compilation problem: \n
         6: invokespecial #21                 // Method java/lang/Error."<init>":(Ljava/lang/String;)V
         9: athrow
      LineNumberTable:
        line 2641: 0
      LocalVariableTable:
        Start  Length  Slot  Name   Signature
            0      10     0  this   Lorg/episteme/nativ/mathematics/linearalgebra/backends/NativeMPFRSparseLinearAlgebraBackend;
      LocalVariableTypeTable:
        Start  Length  Slot  Name   Signature
            0      10     0  this   Lorg/episteme/nativ/mathematics/linearalgebra/backends/NativeMPFRSparseLinearAlgebraBackend<TE;>;

  public Vector<E> projection(Vector<E>, Vector<E>);
    descriptor: (LVector;LVector;)LVector;
    flags: (0x0001) ACC_PUBLIC
    Signature: #167                         // (LVector<TE;>;LVector<TE;>;)LVector<TE;>;
    Code:
      stack=3, locals=3, args_size=3
         0: new           #17                 // class java/lang/Error
         3: dup
         4: ldc           #31                 // String Unresolved compilation problem: \n
         6: invokespecial #21                 // Method java/lang/Error."<init>":(Ljava/lang/String;)V
         9: athrow
      LineNumberTable:
        line 2707: 0
      LocalVariableTable:
        Start  Length  Slot  Name   Signature
            0      10     0  this   Lorg/episteme/nativ/mathematics/linearalgebra/backends/NativeMPFRSparseLinearAlgebraBackend;
      LocalVariableTypeTable:
        Start  Length  Slot  Name   Signature
            0      10     0  this   Lorg/episteme/nativ/mathematics/linearalgebra/backends/NativeMPFRSparseLinearAlgebraBackend<TE;>;

  E createScalar(double, Vector<E>);
    descriptor: (DLVector;)Ljava/lang/Object;
    flags: (0x0000)
    Signature: #248                         // (DLVector<TE;>;)TE;
    Code:
      stack=3, locals=4, args_size=3
         0: new           #17                 // class java/lang/Error
         3: dup
         4: ldc           #31                 // String Unresolved compilation problem: \n
         6: invokespecial #21                 // Method java/lang/Error."<init>":(Ljava/lang/String;)V
         9: athrow
      LineNumberTable:
        line 2727: 0
      LocalVariableTable:
        Start  Length  Slot  Name   Signature
            0      10     0  this   Lorg/episteme/nativ/mathematics/linearalgebra/backends/NativeMPFRSparseLinearAlgebraBackend;
      LocalVariableTypeTable:
        Start  Length  Slot  Name   Signature
            0      10     0  this   Lorg/episteme/nativ/mathematics/linearalgebra/backends/NativeMPFRSparseLinearAlgebraBackend<TE;>;

  E createScalar(org.episteme.core.mathematics.numbers.real.Real, Vector<E>);
    descriptor: (Lorg/episteme/core/mathematics/numbers/real/Real;LVector;)Ljava/lang/Object;
    flags: (0x0000)
    Signature: #250                         // (Lorg/episteme/core/mathematics/numbers/real/Real;LVector<TE;>;)TE;
    Code:
      stack=3, locals=3, args_size=3
         0: new           #17                 // class java/lang/Error
         3: dup
         4: ldc           #31                 // String Unresolved compilation problem: \n
         6: invokespecial #21                 // Method java/lang/Error."<init>":(Ljava/lang/String;)V
         9: athrow
      LineNumberTable:
        line 2738: 0
      LocalVariableTable:
        Start  Length  Slot  Name   Signature
            0      10     0  this   Lorg/episteme/nativ/mathematics/linearalgebra/backends/NativeMPFRSparseLinearAlgebraBackend;
      LocalVariableTypeTable:
        Start  Length  Slot  Name   Signature
            0      10     0  this   Lorg/episteme/nativ/mathematics/linearalgebra/backends/NativeMPFRSparseLinearAlgebraBackend<TE;>;
}
SourceFile: "NativeMPFRSparseLinearAlgebraBackend.java"
Signature: #253                         // <E:Ljava/lang/Object;>Ljava/lang/Object;LSparseLinearAlgebraProvider<TE;>;Lorg/episteme/nativ/technical/backend/nativ/NativeBackend;LCPUBackend;
RuntimeInvisibleAnnotations:
  0: #255(#256=[c#257,c#258,c#259,c#260,c#261,c#262,c#263])
    com.google.auto.service.AutoService(
      value=[class Lorg/episteme/core/technical/backend/Backend;,class Lorg/episteme/core/technical/backend/ComputeBackend;,class Lorg/episteme/nativ/technical/backend/nativ/NativeBackend;,class LLinearAlgebraProvider;,class LSparseLinearAlgebraProvider;,class LCPUBackend;,class Lorg/episteme/core/technical/algorithm/AlgorithmProvider;]
    )
  InconsistentHierarchy: length = 0x0 (unknown attribute)

  MissingTypes: length = 0x18 (unknown attribute)
   00 0B 01 09 01 0B 01 0D 01 0F 01 11 01 13 01 15
   01 17 01 19 01 1B 01 1D
NestMembers:
  org/episteme/nativ/mathematics/linearalgebra/backends/NativeMPFRSparseLinearAlgebraBackend$1
